{
  "stamp": "20260629",
  "generated_at": "2026-06-30T18:40:53",
  "total": 49,
  "categories": [
    "政策",
    "市场",
    "产品",
    "技术",
    "舆情"
  ],
  "category_counts": {
    "政策": 4,
    "市场": 21,
    "产品": 12,
    "技术": 11,
    "舆情": 1
  },
  "brand_counts": {
    "比亚迪": 4,
    "宝马": 3,
    "小米": 3,
    "小鹏": 3,
    "蔚来": 2,
    "领克": 2,
    "法拉利": 2,
    "零跑": 2,
    "福特": 2,
    "理想": 2,
    "丰田": 2,
    "奥迪": 1,
    "雪佛兰": 1,
    "坦克": 1,
    "特斯拉": 1,
    "岚图": 1,
    "问界": 1,
    "深蓝": 1,
    "奇瑞": 1,
    "大众": 1,
    "保时捷": 1,
    "腾势": 1,
    "奔驰": 1,
    "吉利": 1,
    "埃安": 1,
    "广汽": 1,
    "一汽": 1,
    "红旗": 1,
    "现代": 1,
    "东风": 1,
    "长城": 1,
    "日产": 1
  },
  "source_counts": {
    "盖世汽车": 24,
    "汽车之家": 19,
    "汽车公社": 6
  },
  "top": [
    "6b133eadbed082f9",
    "64702d3a0e7de0c5",
    "9b0edba4d8a6dd1c",
    "c004c4ca562ea259",
    "acecc365c03c9cc6",
    "4da5bf3fde22b933",
    "6b86fcd6af81e617",
    "e99c143d42fa3ad0"
  ],
  "items": [
    {
      "title": "预售16.58万元起，领克07GT全球首秀，开创“运动旅行”新品类",
      "url": "https://auto.gasgoo.com/news/202606/29I70463676C109.shtml",
      "publish_time": "2026-06-29 23:26:45",
      "snippet": "获取配套商机，在线申请采购项目 完善公司资料，让采购商深入了解我的生产能力 6月29日，领克汽车旗下首款旅行车领克07GT正式全球首秀并开启预售。新车共推出四驱性能Ultra、200超长续航Ultra、200超长续航Max三个版型，预售价格区间为16.58万元至18.58万元。 同时，领克07GT时间限量版正式上市，首发限量1007台，售价20.88万元。发布会结束当晚，官方便宣布1007台首发限量版已售罄。 作为领克开创“运动旅行”新品类的首款车型，领克07GT承袭了品牌在TCR赛场七年九冠的技术积淀，以超跑同源的MRC磁流变悬架、EM-P智能电混系统、全系标配激光雷达等硬核配置，试图在15-20万元级旅行车市场建立起差异化的产品优势。 从TCR到拉力赛，七年赛事积淀反哺量产底盘 领克07GT的底盘系统是其与同级车型拉开差距的核心筹码。新车搭载的MRC磁流变悬架，此前主要应用于雪佛兰Corvette、法拉利Daytona SP3等超跑车型，在量产旅行车领域尚属首次下放。 这套系统的技术原理是通过磁流变液在磁场作用下的粘度瞬时变化实现阻尼调节，悬架响应时间1ms，系统从感知路面变化到完成阻尼调整仅需10ms，约为CDC连续阻尼悬架响应速度的10倍。在100km/h时速下，车轮每滚动约2.7cm，减震器即可完成一次软硬调节。 从数据上看，MRC悬架的阻尼调节范围最高达10000N（1m/s），相比CDC悬架多出约4000N的冗余。更宽的带宽意味着舒适与操控两端都可调至更极致的状态。领克自研的深度控制算法通过车身传感器识别前方15m范围内的路面特征——包括减速带、坑洼和弯道——提前制定阻尼策略，实现预判式减震。 在中汽中心认证的特殊工况麋鹿测试中，领克07GT在车顶装载行李箱工况下跑出82.1km/h，拖挂装备工况下为81.9km/h，验证了MRC悬架在负载状态下的稳定控制能力。 制动系统方面，新车配备360mm直径、30mm厚度的大尺寸刹车盘与四活塞运动卡钳。卡钳采用对称布局，两侧活塞同步夹紧，制动力输出与踏板力度线性匹配。CST舒适无感制动功能在车辆即将刹停时主动泄压，抑制刹车点头幅度。麋鹿测试成绩为85km/h，领先于蔚来ET5T（81km/h）和奥迪A4 Avant（80km/h）。 这些底盘调校数据的底层支撑来自领克在TCR系列赛的长期积累。自2019年参赛以来，领克累计获得9个年度世界冠军、43个分站冠军，132次登上领奖台。赛场上的悬架标定、阻尼设定、车身姿态控制等数据被系统性地反馈至量产车研发流程，形成了从赛道到街道的技术闭环。领克方面宣布，从今年三季度起，领克07GT将作为官方战车出征拉力赛，在泥泞、碎石等非铺装路面完成性能验证。 动力总成方面，领克07GT搭载EM-P智能电混系统。1.5T Evo电混专用引擎采用350bar直喷系统和高效燃烧",
      "image": "https://imagecn.gasgoo.com/moblogo/News/160_110/2026/6/2911293119.jpg",
      "source": "gasgoo",
      "source_name": "盖世汽车",
      "crawled_at": "2026-06-30T10:31:59.098295+00:00",
      "item_id": "6b133eadbed082f9",
      "publish_ts": 1782746805.0,
      "publish_date": "2026-06-29",
      "image_status": "ok",
      "image_reason": "高置信正文图",
      "category": "产品",
      "brands": [
        "蔚来",
        "奥迪",
        "雪佛兰",
        "领克",
        "法拉利"
      ],
      "importance": 50,
      "summary": "6月29日，领克首款旅行车07GT全球首秀并开启预售，推出四驱性能Ultra、200超长续航Ultra、200超长续航Max三个版本，预售价16.58万至18.58万元；时间限量版售价20.88万元，首发1007台当晚售罄。新车搭载MRC磁流变悬架、EM-P智能电混系统并全系标配激光雷达，MRC悬架响应1ms、完成阻尼调整10ms，麋鹿测试成绩达到85km/h。",
      "takeaway": "领克试图用底盘技术和赛事背书重塑旅行车的性能溢价。",
      "enriched_by": "codex",
      "is_featured": true,
      "has_time": true
    },
    {
      "title": "零跑终于站上了30万的台阶，然后呢？",
      "url": "https://www.iautodaily.com/news/review/lingpaozhongyuzhanshangle30wandetaijieranhoune/",
      "publish_time": "2026-06-29 23:05:00",
      "snippet": "走过平价市场的积累，零跑借 D99 正式叩开 30 万级市场大门，但品牌向上、技术突围的考验才刚刚开始。 2026年6月25日，零跑首款MPV D99正式上市。原定预售，临时改为直接上市，节奏快到超出行业预期。朱江明直言：产品、产能、市场认知全部到位，无需多余营销环节拖延用户交付。 这很符合零跑汽车的一贯风格——效率至上。事实上，从成立之初，零跑就在做同一件事，那就是把成本降下来，把效率提上去，把车子卖出去。 D99作为D平台第二款旗舰，补齐了其品牌的MPV品类空白；依托全域自研，各种豪华溢价配置加持，助推零跑触达到30万级别MPV市场。 毫无疑问，这是一个零跑的里程碑事件。然而其中的问题在于，长久以来市场形成的固有认知，零跑深耕20万以下平价市场，冲击高端MPV必然面临成本与定价的双重挑战。 面对毛利、定价策略等问题，朱江明重申了零跑十年不变的造车准则：更高配置、更优品质、好而不贵，全价位产品统一遵循成本定价逻辑，不依靠品牌收取高额溢价。 D99作为零跑汽车的品牌旗舰，配置标准可以说是直接拉满，全系标配米其林轮胎、博世华宇REPS转向系统、安道拓高端座椅，绝大多数高端配置覆盖入门版本…… 对此，朱江明坦言，D99的单车利润高于A10平价车型，但依旧没有脱离成本定价框架。尽管当下碳酸锂、铜铝、塑料等原材料全线涨价，但零跑依旧会内部消化成本压力，不会涨价。 而依托D19积累的高端用户口碑，零跑对D99的市场表现充满信心。在零跑看来，MPV市场全年规模约百万台，虽体量小于SUV，但宜商宜家双重属性，可以带来稳定增量。 针对行业“大六座SUV可替代MPV”的观点，曹力表示：大尺寸SUV第三排实用性极低，日常基本作为五座车使用；D99第三排拥有独立舒适乘坐空间，座椅布局灵活多变，兼顾多人出行与大件装载，空间属性优势无法被SUV替代。 值得注意的是，本次零跑D99上市给出了一个明显信号——零跑将就此正式告别保守技术跟随策略，转向前沿技术前置落地，全域自研护城河持续拓宽。 硬件层面，零跑持续领跑高通座舱芯片量产落地，8155、8295、8797均实现行业率先大规模装车，下一代8787芯片，也有望优先量产； D99搭载全新4.0中央预控平台，高算力座舱、智驾系统、空气悬架等前沿配置首次下放D系列车型。 软件层面实现全栈自研，从底层控制器、BMS电池管理、电驱动系统到中央预控、座舱、智驾，所有底层代码全部自主开发，不依赖外部第三方方案。 朱江明坦言，零跑在前期的智驾投入相对保守，以跟随迭代为主；但未来两三个月将完成技术突破，三季度零跑专属技术日会集中发布自研创新技术，给行业带来全新技术参考。 没错，零跑要放技术“大招”了。所有前瞻技术，将为明年全新车型铺路。 据称，2027年零跑将推出形态完全区别于现有乘用车的创新产品，同步落地全新第二品牌，进一步细分高端市场，覆盖30万以",
      "image": "https://www.iautodaily.com/wp-content/uploads/2026/05/2026053001452697-480x320.jpg",
      "source": "iautodaily",
      "source_name": "汽车公社",
      "crawled_at": "2026-06-30T10:30:31.771201+00:00",
      "item_id": "64702d3a0e7de0c5",
      "publish_ts": 1782745500.0,
      "publish_date": "2026-06-29",
      "image_status": "ok",
      "image_reason": "高置信正文图",
      "category": "产品",
      "brands": [
        "零跑"
      ],
      "importance": 59,
      "summary": "零跑首款MPV D99于2026年6月25日正式上市，原定预售临时改为直接上市，朱江明称产品、产能和市场认知已到位。D99是D平台第二款旗舰，补齐零跑MPV品类空白，面向30万元级市场，全系标配米其林轮胎、博世华宇REPS转向系统、安道拓高端座椅等配置。零跑强调仍按成本定价，不因品牌收取高溢价，并将高算力座舱、智驾系统和空气悬架下放D系列，计划在三季度技术日发布自研创新技术。",
      "takeaway": "D99检验零跑能否把低成本效率优势迁移到高端用户心智。",
      "enriched_by": "codex",
      "is_featured": true,
      "has_time": true
    },
    {
      "title": "领克07GT预售16.58万起 高颜值/530马力四驱 再也不馋M3旅行了",
      "url": "https://www.autohome.com.cn/news/202606/1315381.html",
      "publish_time": "2026-06-29 21:19",
      "snippet": "",
      "image": "https://img3.autoimg.cn/chejiahaodfs/g33/M05/E6/44/ChxpVmpCcnmAf-nHAA8rXt9xXpM642.png",
      "source": "autohome",
      "source_name": "汽车之家",
      "crawled_at": "2026-06-30T10:31:31.860659+00:00",
      "item_id": "9b0edba4d8a6dd1c",
      "publish_ts": 1782739140.0,
      "publish_date": "2026-06-29",
      "image_status": "ok",
      "image_reason": "高置信正文图",
      "category": "产品",
      "brands": [
        "领克"
      ],
      "importance": 21,
      "summary": "",
      "takeaway": "",
      "enriched_by": "rule",
      "is_featured": false,
      "has_time": true
    },
    {
      "title": "AI攻关与双碳路径并举 两大“十五五”规划过审",
      "url": "https://auto.gasgoo.com/news/202606/29I70463673C1103.shtml",
      "publish_time": "2026-06-29 21:12:19",
      "snippet": "获取配套商机，在线申请采购项目 完善公司资料，让采购商深入了解我的生产能力 盖世汽车6月29日获悉，据央视新闻，国务院总理李强主持召开国务院常务会议，一次性抛出四份重磅文件与发展部署——在听取人工智能发展汇报、研判当前外贸形势的同时，正式审议通过《“十五五”碳达峰行动方案》和《国民健康“十五五”规划》。 人工智能：从“攻关”到“治理”全链条铺开。会议明确，要加快关键技术攻关和超大规模智算集群建设，强化高质量数据供给，“牢牢掌握发展主动权”。值得关注的是，官方首次在国常会层面把“完善科技伦理、测试认证、分级分类安全监管”与“人工智能+”商业落地并列表述——这意味着产业狂奔的同时，伦理与安全已从“软约束”升级为“硬框架”。 外贸：稳规模、提质量、强安全三线并进。面对外部不确定性，会议给出“信贷+信保”政策组合拳，并提出“内外贸一体化”“贸易投资一体化”的新提法，数字贸易、自主开放、涉外安全保障被一并纳入工具箱。 “双碳”：绿色低碳嵌入国民经济循环。《“十五五”碳达峰行动方案》获审议通过，会议强调要把“绿色低碳导向融入国民经济循环各领域各环节”，能源结构优化与产业低碳化并列成为抓手，碳排放统计核算体系则被点名为制度基础设施。 健康：全生命周期服务+新型服务业态。另一份过审的《国民健康“十五五”规划》提出医疗、医保、疾控协同，并首次在国常会语境中强调“培育壮大健康领域新型服务业态”——康养、健康管理等赛道的政策红利窗口正在打开。 本文地址：http://auto.gasgoo.com/News/2019/05/300656465646I70107904C601.shtml 本文地址：https://auto.gasgoo.com/news/202606/29I70463673C1103.shtml 联系邮箱：info@gasgoo.com 求职应聘：021-39197800-8035 简历投递：zhaopin@gasgoo.com 客服微信：gasgoo12 (豆豆) 新闻热线：021-39586122 商务合作：021-39586681 市场合作：021-39197800-8032 研究院项目咨询：021-39197921 盖世汽车社区 盖世大学堂-公开课 英文资讯站 热门内容 数据报告 盖世汽车产业大数据",
      "image": "",
      "source": "gasgoo",
      "source_name": "盖世汽车",
      "crawled_at": "2026-06-30T10:31:59.098295+00:00",
      "item_id": "c004c4ca562ea259",
      "publish_ts": 1782738739.0,
      "publish_date": "2026-06-29",
      "image_status": "empty",
      "image_reason": "无图片",
      "category": "政策",
      "brands": [],
      "importance": 24,
      "summary": "",
      "takeaway": "",
      "enriched_by": "rule",
      "is_featured": false,
      "has_time": true
    },
    {
      "title": "SK Keyfoundry开发出基于双向可控硅（Bi-SCR）的片上EMC防护技术 提升车用半导体的可靠性",
      "url": "https://auto.gasgoo.com/news/202606/29I70463672C409.shtml",
      "publish_time": "2026-06-29 20:47:25",
      "snippet": "获取配套商机，在线申请采购项目 完善公司资料，让采购商深入了解我的生产能力 盖世汽车讯 6月25日，韩国8英寸专业晶圆代工厂SK Keyfoundry宣布，近期开发出一种基于“双向可控硅整流器（Bi-SCR）”的片上EMC（电磁兼容）防护技术，能够显著提升车用半导体的电磁兼容性能。该公司表示，已成功将该技术应用于其0.13微米BCD（双极-CMOS-DMOS）工艺产品，并已投入量产。 本文地址：http://auto.gasgoo.com/News/2019/05/300656465646I70107904C601.shtml *特别声明：本文为技术类文章，禁止转载或大篇幅摘录！违规转载，法律必究。 本文地址：https://auto.gasgoo.com/news/202606/29I70463672C409.shtml 联系邮箱：info@gasgoo.com 求职应聘：021-39197800-8035 简历投递：zhaopin@gasgoo.com 客服微信：gasgoo12 (豆豆) 新闻热线：021-39586122 商务合作：021-39586681 市场合作：021-39197800-8032 研究院项目咨询：021-39197921 盖世汽车社区 盖世大学堂-公开课 英文资讯站 热门内容 数据报告 盖世汽车产业大数据",
      "image": "",
      "source": "gasgoo",
      "source_name": "盖世汽车",
      "crawled_at": "2026-06-30T10:31:59.098295+00:00",
      "item_id": "acecc365c03c9cc6",
      "publish_ts": 1782737245.0,
      "publish_date": "2026-06-29",
      "image_status": "empty",
      "image_reason": "无图片",
      "category": "市场",
      "brands": [],
      "importance": 17,
      "summary": "",
      "takeaway": "",
      "enriched_by": "rule",
      "is_featured": false,
      "has_time": true
    },
    {
      "title": "现款售19.98万起 全新坦克300将于7月6日预售 车身尺寸全面加大",
      "url": "https://www.autohome.com.cn/news/202606/1315380.html",
      "publish_time": "2026-06-29 20:47",
      "snippet": "",
      "image": "https://car2.autoimg.cn/cardfs/product/g34/M01/D3/B8/400x300_0_autohomecar__ChtpWGmz7meAEaoTAA5mzEdCKW4352.jpg",
      "source": "autohome",
      "source_name": "汽车之家",
      "crawled_at": "2026-06-30T10:31:31.860659+00:00",
      "item_id": "4da5bf3fde22b933",
      "publish_ts": 1782737220.0,
      "publish_date": "2026-06-29",
      "image_status": "ok",
      "image_reason": "高置信正文图",
      "category": "产品",
      "brands": [
        "坦克"
      ],
      "importance": 21,
      "summary": "",
      "takeaway": "",
      "enriched_by": "rule",
      "is_featured": false,
      "has_time": true
    },
    {
      "title": "威世推出车规级光电晶体管光耦",
      "url": "https://auto.gasgoo.com/news/202606/29I70463671C409.shtml",
      "publish_time": "2026-06-29 20:45:29",
      "snippet": "获取配套商机，在线申请采购项目 完善公司资料，让采购商深入了解我的生产能力 盖世汽车讯 6月25日，美国电子元件制造商威世科技（Vishay Intertechnology）推出一款全新的车规级光电晶体管光耦，专为电动汽车（EV，包括新兴的800V电池架构）及工业自动化系统中的高电气隔离信号传输而设计。威世Semiconductors VOLA617A采用4引脚LSOP薄型封装，具备5000 VRMS的隔离电压，以及1414 Vpeak的VIORM（最大重复峰值隔离电压）和8000 Vpeak的VIOTM（最大瞬态隔离电压）额定值。 本文地址：http://auto.gasgoo.com/News/2019/05/300656465646I70107904C601.shtml *特别声明：本文为技术类文章，禁止转载或大篇幅摘录！违规转载，法律必究。 本文地址：https://auto.gasgoo.com/news/202606/29I70463671C409.shtml 联系邮箱：info@gasgoo.com 求职应聘：021-39197800-8035 简历投递：zhaopin@gasgoo.com 客服微信：gasgoo12 (豆豆) 新闻热线：021-39586122 商务合作：021-39586681 市场合作：021-39197800-8032 研究院项目咨询：021-39197921 盖世汽车社区 盖世大学堂-公开课 英文资讯站 热门内容 数据报告 盖世汽车产业大数据",
      "image": "",
      "source": "gasgoo",
      "source_name": "盖世汽车",
      "crawled_at": "2026-06-30T10:31:59.098295+00:00",
      "item_id": "6b86fcd6af81e617",
      "publish_ts": 1782737129.0,
      "publish_date": "2026-06-29",
      "image_status": "rejected",
      "image_reason": "同一图片被超过 3 篇文章复用，按站点装饰图处理",
      "category": "技术",
      "brands": [],
      "importance": 24,
      "summary": "",
      "takeaway": "",
      "enriched_by": "rule",
      "is_featured": false,
      "has_time": true
    },
    {
      "title": "福特申请车辆视野系统专利",
      "url": "https://auto.gasgoo.com/news/202606/29I70463670C409.shtml",
      "publish_time": "2026-06-29 20:40:18",
      "snippet": "获取配套商机，在线申请采购项目 完善公司资料，让采购商深入了解我的生产能力 盖世汽车讯 据外媒报道，福特汽车公司（Ford Motor Company）已向美国专利商标局提交一项关于车辆视野系统的专利申请，该系统有望应用于未来的福特车型。该专利于2024年12月15日提交，于2026年6月18日公布，编号为0167105。 近几个月来，福特提交了多项旨在改善车内外视野的专利申请，例如隐蔽物体检测系统和视野遮挡检测系统等。如今，这一趋势仍在延续：福特新近公布了一项专利，提出了一种车辆视野系统概念。 本文地址：http://auto.gasgoo.com/News/2019/05/300656465646I70107904C601.shtml *特别声明：本文为技术类文章，禁止转载或大篇幅摘录！违规转载，法律必究。 本文地址：https://auto.gasgoo.com/news/202606/29I70463670C409.shtml 联系邮箱：info@gasgoo.com 求职应聘：021-39197800-8035 简历投递：zhaopin@gasgoo.com 客服微信：gasgoo12 (豆豆) 新闻热线：021-39586122 商务合作：021-39586681 市场合作：021-39197800-8032 研究院项目咨询：021-39197921 盖世汽车社区 盖世大学堂-公开课 英文资讯站 热门内容 数据报告 盖世汽车产业大数据",
      "image": "",
      "source": "gasgoo",
      "source_name": "盖世汽车",
      "crawled_at": "2026-06-30T10:31:59.098295+00:00",
      "item_id": "e99c143d42fa3ad0",
      "publish_ts": 1782736818.0,
      "publish_date": "2026-06-29",
      "image_status": "rejected",
      "image_reason": "同一图片被超过 3 篇文章复用，按站点装饰图处理",
      "category": "市场",
      "brands": [
        "福特"
      ],
      "importance": 21,
      "summary": "",
      "takeaway": "",
      "enriched_by": "rule",
      "is_featured": false,
      "has_time": true
    },
    {
      "title": "福特申请可收纳式键盘专利",
      "url": "https://auto.gasgoo.com/news/202606/29I70463669C409.shtml",
      "publish_time": "2026-06-29 20:39:12",
      "snippet": "获取配套商机，在线申请采购项目 完善公司资料，让采购商深入了解我的生产能力 盖世汽车讯 据外媒报道，福特汽车公司（Ford Motor Company）已提交一项关于可收纳式键盘的专利，该键盘有望应用于福特未来的车型中。该专利于2025年4月11日提交，于2026年6月23日公布，专利编号为12661988。 过去几个月里，福特提交了一系列专利，旨在将车内空间转变为办公或生活区域——例如可展开的工作台、带有活动桌面的控制台，以及专为放置平板电脑设计的中央控制台等。如今，福特又提交了一项新专利，延续了这一设计理念，提出了一种可收纳式键盘方案。 本文地址：http://auto.gasgoo.com/News/2019/05/300656465646I70107904C601.shtml *特别声明：本文为技术类文章，禁止转载或大篇幅摘录！违规转载，法律必究。 本文地址：https://auto.gasgoo.com/news/202606/29I70463669C409.shtml 联系邮箱：info@gasgoo.com 求职应聘：021-39197800-8035 简历投递：zhaopin@gasgoo.com 客服微信：gasgoo12 (豆豆) 新闻热线：021-39586122 商务合作：021-39586681 市场合作：021-39197800-8032 研究院项目咨询：021-39197921 盖世汽车社区 盖世大学堂-公开课 英文资讯站 热门内容 数据报告 盖世汽车产业大数据",
      "image": "",
      "source": "gasgoo",
      "source_name": "盖世汽车",
      "crawled_at": "2026-06-30T10:31:59.098295+00:00",
      "item_id": "2ada86fcf3577583",
      "publish_ts": 1782736752.0,
      "publish_date": "2026-06-29",
      "image_status": "rejected",
      "image_reason": "同一图片被超过 3 篇文章复用，按站点装饰图处理",
      "category": "市场",
      "brands": [
        "福特"
      ],
      "importance": 21,
      "summary": "",
      "takeaway": "",
      "enriched_by": "rule",
      "is_featured": false,
      "has_time": true
    },
    {
      "title": "特斯拉申请Cybercab独特车轮设计专利",
      "url": "https://auto.gasgoo.com/news/202606/29I70463668C409.shtml",
      "publish_time": "2026-06-29 20:38:12",
      "snippet": "获取配套商机，在线申请采购项目 完善公司资料，让采购商深入了解我的生产能力 盖世汽车讯 据外媒报道，特斯拉向美国专利商标局（USPTO）为其Cybercab车轮的装饰性设计申请了专利，专利号为US-D1130251-S。尽管该外观设计专利并未透露太多技术规格信息，但它进一步印证了此前在公开场合所见的轮胎设计与车轮布局。 这项专利涵盖的车轮设计采用了一种扁平的金色轮毂盖，该轮毂盖可扣合在轮辋上，封闭气流空隙以最大化空气动力学效率。美观考量可能也是促成这一设计的原因之一；特斯拉很可能是利用这种轮毂盖来遮盖厚实的轮胎轮廓及独特的车轮构造。 本文地址：http://auto.gasgoo.com/News/2019/05/300656465646I70107904C601.shtml *特别声明：本文为技术类文章，禁止转载或大篇幅摘录！违规转载，法律必究。 本文地址：https://auto.gasgoo.com/news/202606/29I70463668C409.shtml 联系邮箱：info@gasgoo.com 求职应聘：021-39197800-8035 简历投递：zhaopin@gasgoo.com 客服微信：gasgoo12 (豆豆) 新闻热线：021-39586122 商务合作：021-39586681 市场合作：021-39197800-8032 研究院项目咨询：021-39197921 盖世汽车社区 盖世大学堂-公开课 英文资讯站 热门内容 数据报告 盖世汽车产业大数据",
      "image": "",
      "source": "gasgoo",
      "source_name": "盖世汽车",
      "crawled_at": "2026-06-30T10:31:59.098295+00:00",
      "item_id": "02a535885359d3f6",
      "publish_ts": 1782736692.0,
      "publish_date": "2026-06-29",
      "image_status": "rejected",
      "image_reason": "同一图片被超过 3 篇文章复用，按站点装饰图处理",
      "category": "市场",
      "brands": [
        "特斯拉"
      ],
      "importance": 21,
      "summary": "",
      "takeaway": "",
      "enriched_by": "rule",
      "is_featured": false,
      "has_time": true
    },
    {
      "title": "英国研究联盟发布更轻的铝制副车架",
      "url": "https://auto.gasgoo.com/news/202606/29I70463667C409.shtml",
      "publish_time": "2026-06-29 20:36:45",
      "snippet": "获取配套商机，在线申请采购项目 完善公司资料，让采购商深入了解我的生产能力 盖世汽车讯 据外媒报道，由英国主导的一个联盟发布了先进的铸铝汽车副车架。这些部件有望通过大幅减轻重量、降低开发成本并缩短生产周期，推动汽车制造业的变革。 这些部件是在耗资580万英镑的“高性能集成车辆优化技术”（Performance Integrated Vehicle Optimisation Technology，PIVOT）项目下开发的；与某家英国大型整车制造商（OEM）一款演示车型上的原有结构相比，新部件的前部和后部重量分别减轻了17%和35%。 这一突破性成果在由谢菲尔德大学先进制造研究中心（AMRC）主办的“铸就铝业未来”（Casting the Future of Aluminium）活动上正式发布，彰显了先进铸造技术与虚拟工程技术在支持下一代轻量化、高性能汽车方面的巨大潜力。 本文共计1013字开通高级账号后继续阅读 本文共计1013字开通高级账号后继续阅读 本文地址：http://auto.gasgoo.com/News/2019/05/300656465646I70107904C601.shtml *特别声明：本文为技术类文章，禁止转载或大篇幅摘录！违规转载，法律必究。 本文地址：https://auto.gasgoo.com/news/202606/29I70463667C409.shtml 联系邮箱：info@gasgoo.com 求职应聘：021-39197800-8035 简历投递：zhaopin@gasgoo.com 客服微信：gasgoo12 (豆豆) 新闻热线：021-39586122 商务合作：021-39586681 市场合作：021-39197800-8032 研究院项目咨询：021-39197921 盖世汽车社区 盖世大学堂-公开课 英文资讯站 热门内容 数据报告 盖世汽车产业大数据",
      "image": "",
      "source": "gasgoo",
      "source_name": "盖世汽车",
      "crawled_at": "2026-06-30T10:31:59.098295+00:00",
      "item_id": "ee6ca437f83a4b03",
      "publish_ts": 1782736605.0,
      "publish_date": "2026-06-29",
      "image_status": "rejected",
      "image_reason": "同一图片被超过 3 篇文章复用，按站点装饰图处理",
      "category": "市场",
      "brands": [],
      "importance": 24,
      "summary": "",
      "takeaway": "",
      "enriched_by": "rule",
      "is_featured": false,
      "has_time": true
    },
    {
      "title": "UNECE通过允许全自动驾驶汽车的法规",
      "url": "https://auto.gasgoo.com/news/202606/29I70463666C409.shtml",
      "publish_time": "2026-06-29 20:34:28",
      "snippet": "获取配套商机，在线申请采购项目 完善公司资料，让采购商深入了解我的生产能力 盖世汽车讯 尽管早先关于自动驾驶将广泛普及的预测未能如期实现，但十年后的今天，全球监管格局已迎来一个决定性的里程碑。据外媒报道，联合国欧洲经济委员会（UNECE）“世界车辆法规协调论坛”（WP.29）已通过全球首个针对完全无人驾驶自动驾驶系统（ADS）的监管框架。 该新框架确立了统一的国际安全要求以及针对配备自动驾驶系统车辆的通用验证方法。它基于“安全论证”（safety-case）理念与安全管理体系，旨在确保自动驾驶系统符合严格且以结果为导向的安全标准，从而增强政府、产业界与公众之间的信任。 WP.29的这一决定凸显了全球统一车辆法规日益增长的重要性。该法规避免了各国监管标准不一的局面，不仅为制造商提供了明确指引，增强了消费者信心，还为创新成果在各市场间的安全规模化推广开辟了路径。该法规将于约一个月后正式生效。 本文地址：http://auto.gasgoo.com/News/2019/05/300656465646I70107904C601.shtml *特别声明：本文为技术类文章，禁止转载或大篇幅摘录！违规转载，法律必究。 本文地址：https://auto.gasgoo.com/news/202606/29I70463666C409.shtml 联系邮箱：info@gasgoo.com 求职应聘：021-39197800-8035 简历投递：zhaopin@gasgoo.com 客服微信：gasgoo12 (豆豆) 新闻热线：021-39586122 商务合作：021-39586681 市场合作：021-39197800-8032 研究院项目咨询：021-39197921 盖世汽车社区 盖世大学堂-公开课 英文资讯站 热门内容 数据报告 盖世汽车产业大数据",
      "image": "",
      "source": "gasgoo",
      "source_name": "盖世汽车",
      "crawled_at": "2026-06-30T10:31:59.098295+00:00",
      "item_id": "a5343070e3305678",
      "publish_ts": 1782736468.0,
      "publish_date": "2026-06-29",
      "image_status": "rejected",
      "image_reason": "同一图片被超过 3 篇文章复用，按站点装饰图处理",
      "category": "政策",
      "brands": [],
      "importance": 17,
      "summary": "",
      "takeaway": "",
      "enriched_by": "rule",
      "is_featured": false,
      "has_time": true
    },
    {
      "title": "将全天的光影美学融进车身 岚图追光S将提供7种车身颜色可选",
      "url": "https://www.autohome.com.cn/news/202606/1315375.html",
      "publish_time": "2026-06-29 17:48",
      "snippet": "",
      "image": "https://www2.autoimg.cn/chejiahaodfs/g33/M05/E4/29/400x300_0_autohomecar__Chto52pCPjyADFhbAAtZ5msJBQs911.png",
      "source": "autohome",
      "source_name": "汽车之家",
      "crawled_at": "2026-06-30T10:31:31.860659+00:00",
      "item_id": "d1b88254b5bda950",
      "publish_ts": 1782726480.0,
      "publish_date": "2026-06-29",
      "image_status": "ok",
      "image_reason": "高置信正文图",
      "category": "市场",
      "brands": [
        "岚图"
      ],
      "importance": 14,
      "summary": "",
      "takeaway": "",
      "enriched_by": "rule",
      "is_featured": false,
      "has_time": true
    },
    {
      "title": "全景视域桥+倾斜中控屏+副驾屏 全新宝马X5内饰疑似提前曝光",
      "url": "https://www.autohome.com.cn/news/202606/1315374.html",
      "publish_time": "2026-06-29 16:56",
      "snippet": "",
      "image": "https://www2.autoimg.cn/chejiahaodfs/g33/M07/E3/63/400x300_0_autohomecar__ChxpVWpCL_GAaLVAAA5_tRKy4w8409.png",
      "source": "autohome",
      "source_name": "汽车之家",
      "crawled_at": "2026-06-30T10:31:31.860659+00:00",
      "item_id": "fab2b701f95f2c68",
      "publish_ts": 1782723360.0,
      "publish_date": "2026-06-29",
      "image_status": "ok",
      "image_reason": "高置信正文图",
      "category": "产品",
      "brands": [
        "宝马"
      ],
      "importance": 14,
      "summary": "",
      "takeaway": "",
      "enriched_by": "rule",
      "is_featured": false,
      "has_time": true
    },
    {
      "title": "增程的尽头，到底是什么？",
      "url": "https://auto.gasgoo.com/news/202606/29I70463638C501.shtml",
      "publish_time": "2026-06-29 16:45:07",
      "snippet": "获取配套商机，在线申请采购项目 完善公司资料，让采购商深入了解我的生产能力 在全新理想L8发布会前，理想汽车CEO李想提前抛出了这个问题。当晚，理想给出了自己的答案：\"增程的尽头，是理想5C增程。\" 隔日，蔚来副总裁马麟在微博上打出\"谢谢\"二字，并引述蔚来创始人李斌此前的公开表态：感谢增程车型在过去几年中培养了用户用电的习惯，为纯电车型的普及打下了基础。 蔚来早有定论，口号掷地有声：\"增程的尽头是纯电，纯电的尽头是换电。\" 两种立场，各执一端。争论之所以激烈，是因为它触及了新能源转型最核心的命题——一条曾被视为\"过渡方案\"的技术路线，究竟会走向终结，还是走向进化？ 增程的崛起曾是中国新能源市场最令人意外的故事。 2020年，增程车全年销量不过3万辆。四年后，这条赛道以近乎垂直的曲线冲上云霄——2024年国内增程车型批发51.4万辆，同比增幅高达78.7%。2025年，市场体量进一步扩容至123万辆，一度占据新能源市场超10%的份额。\"可油可电\"成了最动人的卖点，精准击中了早期电动车用户的里程焦虑。 乘联分会数据显示，2026年5月国内增程车型批发销量仅9.5万辆，同比暴跌24.9%，创近五年最大单月跌幅。1至5月累计销售41万辆，同比下滑9.7%，市场份额从2025年同期的10.3%缩至7.0%。更残酷的是产品端——5月全市场仅有3款增程车型月销量突破5000辆，新能源销量前十榜单仅保留一款增程车型。 龙头车企的战略换挡是核心推手。2025年5月，理想交付40856辆，几乎全是增程；2026年5月，理想交付33350辆，纯电i6已连续三个月突破2万辆。一年之间，理想一家增程单月减量接近2.9万辆，几乎等于全行业同比减量的全部。零跑、深蓝等曾经深耕增程的品牌同步调整资源，增量开始依靠纯电支撑。仅问界仍靠产品矩阵维持增程正增长，但无法对冲行业整体颓势。 三重因素正在加速退潮。一是快速补能技术的成熟。800V高压平台大规模量产，10至15分钟快充即可补充300公里以上续航，全国公共充电桩突破500万根，全球最大规模的充电网络已初步建成。二是成本天平的倾斜。电池包均价从2023年的910元/kWh降至620元/kWh，纯电与增程的价差几乎被抹平，而油价持续攀升，直接推高了增程的拥车成本。三是政策端的收紧。2026年起，增程车型若要享受购置税优惠，需同时满足WLTC工况等效纯电续航不低于100公里且馈电油耗优于同级燃油车30%，早年小电池增程产品受到直接冲击。 乘联会秘书长崔东树判断，本轮下滑并非短期淡季波动，而是纯电技术成熟、车企战略转向叠加政策收紧共同形成的结构性拐点。 增程的故事远未终结。关于它的尽头，市场给出了三种截然不同的答案。 第一种答案：纯电。蔚来是这一立场的坚定代表。\"增程的尽头是纯电，纯电的尽头是换电\"，逻辑很清晰：增程培养了用户用电的习惯，随着电池",
      "image": "",
      "source": "gasgoo",
      "source_name": "盖世汽车",
      "crawled_at": "2026-06-30T10:31:59.098295+00:00",
      "item_id": "2d196f7eb616a411",
      "publish_ts": 1782722707.0,
      "publish_date": "2026-06-29",
      "image_status": "rejected",
      "image_reason": "同一图片被超过 3 篇文章复用，按站点装饰图处理",
      "category": "技术",
      "brands": [
        "理想",
        "蔚来",
        "问界",
        "零跑",
        "深蓝"
      ],
      "importance": 64,
      "summary": "围绕“增程尽头”的讨论，理想、蔚来等车企给出不同判断。2020年国内增程车销量不足3万辆，2024年批发51.4万辆，2025年扩大至123万辆、占新能源市场超10%。但2026年5月批发仅9.5万辆，同比下降24.9%，1至5月累计41万辆、份额降至7.0%。理想、零跑、深蓝等转向纯电，800V快充、电池包均价下行、公共充电桩突破500万根和购置税新规共同压缩增程空间。",
      "takeaway": "增程仍有场景价值，但增长逻辑正从普及红利转向产品效率竞争。",
      "enriched_by": "codex",
      "is_featured": true,
      "has_time": true
    },
    {
      "title": "大湾区“首家”之争升级",
      "url": "https://auto.gasgoo.com/news/202606/29I70463637C601.shtml",
      "publish_time": "2026-06-29 16:24:19",
      "snippet": "获取配套商机，在线申请采购项目 完善公司资料，让采购商深入了解我的生产能力 6月29日，具身智能赛道迎来了戏剧性的一刻。大湾区两家企业——自变量机器人与智平方，相继官宣完成新融资，且估值突破200亿元大关。 不仅如此，两家公司均宣称自己是\"大湾区首家\"估值破200亿的具身智能企业。 这场撞车式的宣言，某种程度上也是当下具身智能赛道里，资本野心、行业焦虑与话语权争夺的集体缩影。 6月29日，智平方宣布已于近日完成新系列融资。本轮融资额近50亿元，投后智平方估值飙升至超200亿元，成为粤港澳大湾区首个估值突破200亿的具身智能企业。 据悉，智平方本轮投资方名单实现了“国家队-部委-大湾区-险资-券商-产业方-财投”全链条资本全覆盖，包括国家中小企业体系基金、中国文化产业体系基金、广东省人工智能基金、深创投、南山战新投、粤港澳大湾区系列基金、中国生物制药、康龙化成、茅台集团、招商局资本、五洲新春、中金资本、中信建投、梁创投、锡创投、君礼资本等。 这也是智平方今年完成的第二轮大额融资，在此之前，该公司曾于2月完成B轮融资，规模超10亿元。 智平方成立于2023年4月，主要聚焦生产力型通用智能机器人的研发、生产与服务。为此，智平方自成立就坚持端到端大模型技术范式，自主研发了首个全域全身具身大模型Alpha Brain，并围绕Alpha Brain正向设计研发了AlphaBot系列机器人。 此前，AlphaBot系列已在多个领域实现规模化部署，包括：深入汽车、生物科技及半导体面板显示（如惠科）等高端场景，执行分拣、转运、贴标等任务。 在新零售领域，智平方2025年底推出的模块化具身智能服务空间“智魔方”，已在北京、深圳等多地常态化运营，未来三年，智平方计划落地1000个智魔方，开辟工业之外的新增量曲线。 几乎是同一时间，自变量机器人也宣布已于近日连续完成4轮重磅融资，且已全部完成交割，估值突破200亿元，成为大湾区首个估值破200亿元的具身智能企业。 据悉，自变量本轮融资汇集了各个领域最顶级的资本，目前已经确定的投资方包括中国移动、国家人工智能产业投资基金、红杉中国、IDG资本、源码资本、达晨财智、中金资本、58 集团、沈阳汽车、奇瑞汽车、荣耀等30多家顶级机构、互联网巨头资本、产业资本、国家和地方基金。 值得关注的是，在已知的公开信息中，自变量机器人也是国内具身智能企业中，唯一一家获得美团、阿里、字节跳动和小米四大互联网厂商分别领投，并多次加注的企业。其中小米战投，更是连续参与了三轮融资。 自变量自成立以来，始终坚持自研物理世界原生的基础模型，通过构建AI原生的软硬一体解决方案，实际服务于真正有用的商业和生活场景。据了解，自变量也是国内最早采用完全端到端路径、实现通用具身智能大模型的企业。 在自变量机器人创始人兼CEO王潜看来，具身智能的下一阶段竞争，本质上还是数据闭",
      "image": "https://imagecn.gasgoo.com/moblogo/News/160_110/2026/6/2904221700.jpg",
      "source": "gasgoo",
      "source_name": "盖世汽车",
      "crawled_at": "2026-06-30T10:31:59.098295+00:00",
      "item_id": "bf004cf18cc62df1",
      "publish_ts": 1782721459.0,
      "publish_date": "2026-06-29",
      "image_status": "ok",
      "image_reason": "高置信正文图",
      "category": "市场",
      "brands": [
        "小米",
        "奇瑞"
      ],
      "importance": 32,
      "summary": "6月29日，具身智能企业智平方和自变量机器人相继宣布新融资，且均称估值突破200亿元，并争夺“大湾区首家”标签。智平方本轮融资近50亿元，投资方覆盖国家队、部委、大湾区基金、险资、券商、产业方和财投等，2月还完成超10亿元B轮融资。自变量则连续完成4轮融资，投资方包括中国移动、国家人工智能产业投资基金、红杉中国、IDG资本、58集团、沈阳汽车、奇瑞汽车、荣耀等30多家机构。",
      "takeaway": "估值竞赛背后，具身智能头部公司正在争夺资本、客户和叙事入口。",
      "enriched_by": "codex",
      "is_featured": true,
      "has_time": true
    },
    {
      "title": "HUAWEI HiCar适配等多项功能 比亚迪旗下多款车型迎新一轮OTA升级",
      "url": "https://www.autohome.com.cn/news/202606/1315373.html",
      "publish_time": "2026-06-29 16:22",
      "snippet": "",
      "image": "https://www2.autoimg.cn/chejiahaodfs/g33/M02/E3/02/400x300_0_autohomecar__ChxpVWpCKR2AezXqAAe-XzFJQR0607.png",
      "source": "autohome",
      "source_name": "汽车之家",
      "crawled_at": "2026-06-30T10:31:31.860659+00:00",
      "item_id": "2bdd06bc1d0cd10e",
      "publish_ts": 1782721320.0,
      "publish_date": "2026-06-29",
      "image_status": "ok",
      "image_reason": "高置信正文图",
      "category": "产品",
      "brands": [
        "比亚迪"
      ],
      "importance": 14,
      "summary": "",
      "takeaway": "",
      "enriched_by": "rule",
      "is_featured": false,
      "has_time": true
    },
    {
      "title": "众泰汽车，又要行了？",
      "url": "https://auto.gasgoo.com/news/202606/29I70463619C109.shtml",
      "publish_time": "2026-06-29 16:09:21",
      "snippet": "获取配套商机，在线申请采购项目 完善公司资料，让采购商深入了解我的生产能力 近日，印尼BPKN主席穆罕默德·穆夫提·穆巴拉克博士带队商务考察团，专程到访众泰汽车对接合作。双方经过实地走访、深度座谈，初步敲定新能源汽车全产业链合作意向，涵盖海外建厂、技术输出、动力电池配套、本土人才培养、东南亚市场布局等多项核心内容。 曾经濒临破产、淡出主流视野的众泰，难道要借着东南亚市场翻盘复活？ 这个猜测并非空穴来风。纵观众泰近几年的走势，堪称跌宕起伏。从深陷债务危机、产销停摆、进入破产重整，到新股东入局接手、完成内部重整梳理，如今主动牵手印尼官方、落地出海规划，众泰的发展逻辑正在被改写。 只是需要明确，目前所有合作均为初步意向，无正式签约落地，这场“复活试探”依然充满不确定性。 放在几年前，几乎没人会相信众泰还有重启发展的机会。 曾经的众泰，靠着高性价比车型快速抢占市场，但在汽车行业电动化、智能化的大洗牌中，短板暴露。 技术更新滞后、产品竞争力不足、品控体系落后，叠加行业门槛持续抬升，众泰一步步丢掉市场份额，陷入产销停滞、债务缠身的绝境，最终走上破产重整的道路，基本彻底退出了竞争激烈的国内乘用车主流市场。 就在企业濒临出局的关键时刻，新股东入局托底。通过一系列债务重组、股权更迭、架构优化，众泰稳住了基本盘。更关键的是，重整后的众泰，保留了整车生产资质、四大核心制造工艺，以及一套成熟的零部件供应链体系。 简单来说：壳保住了、造车的底子还在，只是失去了国内市场的生存空间。 如今的国内新能源市场，早已是头部车企的天下。内卷加剧、价格战频发、技术壁垒越来越高，没有核心优势的中小车企，根本没有突围的可能。对众泰而言，死守国内红海市场，只会持续沉寂，几乎没有翻盘机会。 印尼市场的特质，刚好精准匹配众泰的现状。当地坐拥丰富的镍矿资源，是动力电池核心原材料产地，新能源发展潜力巨大。但短板也十分突出：本土整车制造体系不完善，动力电池产业链缺失，急需成熟车企落地补齐产业短板。 一边是完备的造车技术与供应链，一边是广阔的空白市场与资源优势，双方的合作，本质是一场双向互补。 不同于很多车企简单的整车出口试水，众泰这次的出海规划，步子稳、布局全，针对性极强，也是其试图重启经营的核心底牌。 根据双方初步沟通的意向，项目采用分阶段落地的模式，循序渐进、降低风险，逐步扎根印尼市场。 一期优先采用SKD散件组装模式快速投产。这种模式投入低、周期短、见效快，能让众泰快速切入印尼市场。同时在落地过程中逐步提升零部件本地化率，适配当地政策，快速实现产品落地销售，先打通基本的市场通路。 二期则着眼长期深耕，规划建设年产15万台的一体化智能工厂。新工厂将配齐整车冲压、焊装、涂装、总装全流程工艺，还同步配套动力电池产线，补齐印尼本地新能源产业链短板。产品端也精准对标东南亚市场，布局家用新能源车、城市物流车、皮卡等适配",
      "image": "https://imagecn.gasgoo.com/moblogo/News/160_110/2026/6/3012042689.jpg",
      "source": "gasgoo",
      "source_name": "盖世汽车",
      "crawled_at": "2026-06-30T10:31:59.098295+00:00",
      "item_id": "d7ce02a6bd038f3a",
      "publish_ts": 1782720561.0,
      "publish_date": "2026-06-29",
      "image_status": "ok",
      "image_reason": "高置信正文图",
      "category": "市场",
      "brands": [],
      "importance": 38,
      "summary": "印尼BPKN主席穆罕默德·穆夫提·穆巴拉克博士近日率商务考察团到访众泰汽车，双方初步敲定新能源汽车全产业链合作意向，涉及海外建厂、技术输出、动力电池配套、本土人才培养和东南亚市场布局。众泰经历债务危机、产销停摆和破产重整后，仍保留整车生产资质、四大制造工艺及零部件供应链。合作规划一期采用SKD散件组装，二期建设年产15万台智能工厂，并配套动力电池产线，面向家用车、物流车和皮卡等需求。",
      "takeaway": "众泰若想借印尼重启，成败取决于意向合作能否变成稳定产销闭环。",
      "enriched_by": "codex",
      "is_featured": true,
      "has_time": true
    },
    {
      "title": "云境挥杆·驭见臻雅 劳斯莱斯汽车上海·浦东高尔夫私享赛优雅收官",
      "url": "https://www.iautodaily.com/news/yunjinghuiganyujianzhenyalaosilaisiqicheshanghaipudonggaoer/",
      "publish_time": "2026-06-29 16:08:00",
      "snippet": "6 月 26 日，劳斯莱斯汽车上海・浦东携手上海颖奕安亭高尔夫俱乐部共同举办的“云境挥杆・驭见臻雅”高尔夫私享赛于上海圆满收官。赛事以“挑战自我、融于自然”为主旨，以纯粹至臻的奢华礼遇，为品牌挚友们缔造不可复刻的专属体验。 初夏绿意间，一场关于风范、精准与从容雅致的高尔夫私享赛悠然启幕。漫野层林、和风细草间，嘉宾凝神测算坡度与风向，从容挥杆出击，于开阔天地间挑战自我、舒展身心，充分享受高尔夫这一绅士竞技的悠然意趣。劳斯莱斯幻影与古思特Extended静立场边，展露非凡风姿与优雅气度，与高尔夫运动的高雅有度相得益彰。挥杆之际，劳斯莱斯汽车上海・浦东与嘉宾们以球会友、深度叙谈，进一步了解客户的人生故事、非凡洞见，以及对梦想座驾的无限期许。 暮色轻垂，晚星渐起，一日高球竞技缓缓落下帷幕，到场嘉宾与劳斯莱斯汽车上海・浦东团队共赴晚宴雅叙。星光佐酒，致敬每一位赛事奖项的获得者，与尽兴挥杆的品牌挚友。 果岭之外，风雅继续。劳斯莱斯汽车上海・浦东始终致力于为客户打造独一无二的臻享体验，期待与您共赴下一段非凡旅程。 巨星汽车集团旗下劳斯莱斯汽车上海浦东于 2019 年 3 月21日开业，是劳斯莱斯汽车（Rolls-Royce Motor Cars）在上海地区的授权经销商之一，采用劳斯莱斯汽车全新品牌视觉设计体系的精品店，打破传统汽车行业零售方式，将数字化手段和奢侈品体验相结合，为顾客提供无与伦比的高级定制服务。巨星汽车集团作为劳斯莱斯汽车品牌的授权经销商，拥有丰富的超豪华零售经验。集团在大中华区已开设了劳斯莱斯汽车南宁店，劳斯莱斯汽车上海浦东店，劳斯莱斯汽车深圳南山店。我们始终秉承着以客户为中心的理念，并不断突破创新，为顾客创造令人深刻铭记的定制体验。我们高效专业的工作团队将精益求精，致力于以高品质、全方位的服务让顾客感受到劳斯莱斯享誉百年的“领启不凡”品牌核心，以及“力臻完美”的理念。 作为纯粹至简设计理念的典范，古思特表面的凝练简约背后则并不简单——无比深刻复杂的设计、工程技术、手工艺，以及动力科技，建构出这款奢华座驾的卓越特质。古思特Extended 车型较古思特加长170毫米，为后排乘客提供了更加优渥的尊享空间，同时依然保有高贵雅致的车身比例及姿态。客户还可委托定制劳斯莱斯可倾倒的“宁静座椅”，以及专属香槟冷柜。该香槟冷柜可支持6摄氏度和11摄氏度两种制冷模式，能够令客户享受时刻处于最佳饮用温度的香槟佳酿。 劳斯莱斯始终致力于通过Bespoke高级定制卓越复杂的技术和多样化的工艺，帮助客户表达自我卓尔不群的审美情趣与鉴赏品位。古思特Extended运用了劳斯莱斯在织物领域持续探索的最新成果——“交织格纹”，是一种由竹子制成的新型纤维织就的美妙材质，其图案基于对劳斯莱斯品牌两位创始人姓氏首字母“R”交织图案的抽象诠释，并以极富艺术韵味的方式编织为格纹。同时，客户还可选",
      "image": "https://www.iautodaily.com/wp-content/uploads/2026/06/c-users-cao-jiadong-desktop-3-1_-jpg3-1_-480x320.jpeg",
      "source": "iautodaily",
      "source_name": "汽车公社",
      "crawled_at": "2026-06-30T10:30:31.771201+00:00",
      "item_id": "d488c81f108aff2f",
      "publish_ts": 1782720480.0,
      "publish_date": "2026-06-29",
      "image_status": "ok",
      "image_reason": "高置信正文图",
      "category": "市场",
      "brands": [],
      "importance": 13,
      "summary": "",
      "takeaway": "",
      "enriched_by": "rule",
      "is_featured": false,
      "has_time": true
    },
    {
      "title": "国家出手，改装车的春天要来了？",
      "url": "https://www.iautodaily.com/news/review/guojiachushougaizhuangchedechuntianyaolaile/",
      "publish_time": "2026-06-29 15:49:43",
      "snippet": "改装从来就是灰色地带，要想真正改变现状，光靠政策提振还是远远不够的。 长久以来，中国汽车改装行业始终游走在产业舆论的夹缝之中，深陷一种极为荒诞的行业悖论：改装配件可以合法生产、合规销售、公开流通，完整的上下游商贸体系早已成熟，但终端车主的改装行为，却长期处于法律监管的灰色地带。“1087”就像行走的CCTV，时刻监控着改装车的一举一动。 一边，这套“产销合法、改装违法”的错位规则，困住了一个规模万亿、潜力无限的汽车后市场赛道，那另一边，随着中国汽车产业全面和国际接轨，这种不清不楚的商业逻辑，实在有违汽车大国的发展现状。 过去二十余年，国内汽车产业的发展重心始终聚焦于整车制造、新车销售、新能源转型等前端赛道，政策红利、资本资源、行业关注度都高度集中在方面。 对此，人人都认可，相比这类产业命运的抉择，决定讲究个性的改装产业，完全可以往后让一让。更何况，商用和民用改装市场界线，始终都没在法条中有所区别，国家哪来精力去协调所谓的个性输出。“为了那碟醋，去包盘饺子”毫无性价比可言。 直到这一次，当商务部联合工信部、公安部等九部门印发《关于培育壮大汽车后市场消费若干措施的通知》中，首次从国家顶层设计层面，有意为汽车改装行业划定合规边界、完善管理制度、搭建标准体系，这一道原本被虚掩的窄门或将被正式推开。 说白了，随着汽车行业步入理性发展，汽车开始从原来的生产资料或是交通工具层面，迈向准快消品的阶段，汽车市场的前端大环境却不那么景气时，以改装车市场为代表的后市场消费力，能被人看见，无疑是表明一个新的立场：这些由汽车产业进化而来的边际效应，或许能有效缓解行业当前的生存压力。 这不仅是一次简单的政策松绑，更是中国汽车后市场规范化、规模化、品牌化发展的里程碑，标志着国内汽车改装行业正式告别野蛮生长的旧时代，迈入政策护航、市场主导、合规发展的全新周期。而对于车企来说，如果汽车改装能逐步放开，亦是从消费端在推动全行业走出价格战，舆论战的泥淖，再次将工作重点放在整个产业生态的建设上去。 早在两年前，就有数据统计显示，中国汽车改装的市场规模在2024年就突破了1200亿元，同比上一年增长了15%。其中，新能源汽车改装增速较快，已占到整体市场规模的35%左右。 而对于去年的市场变化，中国汽车工业协会监事长姚杰更是指出，2025年中国汽车改装市场规模约1600亿元，渗透率不足5%，与欧美日等成熟市场55%左右渗透率相比，有充足的增长空间。 综合这样的行业现状，不说，汽车改装作为汽车产业链的延伸和价值链的拓展，能否对于激发消费活力、丰富汽车文化、推动产业升级具有重要作用。单从经济层面去考虑，都是一笔不错的“生意”。 回看这一行业的发展历程，我们非常清楚，改装在中国意味着什么。“灰色地带”是贯穿始终的核心标签，而规则错位就是行业难以壮大的根源。 在国内汽车产业的监管体系中，车辆上路合规性始终以出",
      "image": "https://www.iautodaily.com/wp-content/uploads/2026/06/2026062907484786-480x320.jpg",
      "source": "iautodaily",
      "source_name": "汽车公社",
      "crawled_at": "2026-06-30T10:30:31.771201+00:00",
      "item_id": "ebdce4009edb9107",
      "publish_ts": 1782719383.0,
      "publish_date": "2026-06-29",
      "image_status": "ok",
      "image_reason": "高置信正文图",
      "category": "政策",
      "brands": [],
      "importance": 20,
      "summary": "",
      "takeaway": "",
      "enriched_by": "rule",
      "is_featured": false,
      "has_time": true
    },
    {
      "title": "保时捷生产线回迁德国",
      "url": "https://auto.gasgoo.com/news/202606/29I70463627C109.shtml",
      "publish_time": "2026-06-29 15:23:30",
      "snippet": "获取配套商机，在线申请采购项目 完善公司资料，让采购商深入了解我的生产能力 盖世汽车讯 据德国《法兰克福汇报》近日报道，为盘活德国本土工厂闲置产能，保时捷计划把卡宴车型的生产线从斯洛伐克布拉迪斯拉发（Bratislava）转移至其德国莱比锡（Leipzig）工厂。 报道援引保时捷内部员工消息，本次搬迁涵盖保时捷这款大型豪华SUV全部三种动力版本。不过，斯洛伐克人工成本更低，此次产能转移能否落地，取决于德国员工代表是否同意大幅降薪。 彭博新闻社就此消息向保时捷求证时，公司未予置评。 《法兰克福汇报》同时提到，保时捷发言人确认正在与员工代表展开谈判，但没有回应迁厂至莱比锡一事。 保时捷新任首席执行官迈克尔·莱特斯（Michael Leiters）于近日向股东表示，公司将精简车型阵容以提升运营效率，同时深化在大众集团内部的合作，以压缩研发开支。 除了此前敲定的到2029年裁减3,900个岗位的计划外，这位新首席执行官还在推进新一轮降本举措。据悉，保时捷将于今年10月7日的公司资本市场日公布其完整战略细则。 此外，《法兰克福汇报》还称，保时捷位于斯图加特附近的楚芬豪森（Zuffenhausen）总部以及魏斯阿赫（Weissach）研发中心，将有上千个岗位面临缩减。 本文地址：http://auto.gasgoo.com/News/2019/05/300656465646I70107904C601.shtml 本文地址：https://auto.gasgoo.com/news/202606/29I70463627C109.shtml 联系邮箱：info@gasgoo.com 求职应聘：021-39197800-8035 简历投递：zhaopin@gasgoo.com 客服微信：gasgoo12 (豆豆) 新闻热线：021-39586122 商务合作：021-39586681 市场合作：021-39197800-8032 研究院项目咨询：021-39197921 盖世汽车社区 盖世大学堂-公开课 英文资讯站 热门内容 数据报告 盖世汽车产业大数据",
      "image": "https://imagecn.gasgoo.com/moblogo/News/160_110/2026/6/2903232696.jpg",
      "source": "gasgoo",
      "source_name": "盖世汽车",
      "crawled_at": "2026-06-30T10:31:59.098295+00:00",
      "item_id": "e14af03b6d166d37",
      "publish_ts": 1782717810.0,
      "publish_date": "2026-06-29",
      "image_status": "ok",
      "image_reason": "高置信正文图",
      "category": "市场",
      "brands": [
        "大众",
        "保时捷"
      ],
      "importance": 25,
      "summary": "",
      "takeaway": "",
      "enriched_by": "rule",
      "is_featured": false,
      "has_time": true
    },
    {
      "title": "新增智能防晕车等功能 2026款腾势Z9GT迎来首次OTA升级",
      "url": "https://www.autohome.com.cn/news/202606/1315371.html",
      "publish_time": "2026-06-29 15:09",
      "snippet": "",
      "image": "https://www2.autoimg.cn/chejiahaodfs/g33/M09/E1/B2/400x300_0_autohomecar__ChxpVWpCEiqAeVjeABBn3-NnNdM044.png",
      "source": "autohome",
      "source_name": "汽车之家",
      "crawled_at": "2026-06-30T10:31:31.860659+00:00",
      "item_id": "c3c546515f2b5c41",
      "publish_ts": 1782716940.0,
      "publish_date": "2026-06-29",
      "image_status": "ok",
      "image_reason": "高置信正文图",
      "category": "技术",
      "brands": [
        "腾势"
      ],
      "importance": 14,
      "summary": "",
      "takeaway": "",
      "enriched_by": "rule",
      "is_featured": false,
      "has_time": true
    },
    {
      "title": "Momenta IPO，为何14家抢筹？",
      "url": "https://auto.gasgoo.com/news/202606/29I70463625C601.shtml",
      "publish_time": "2026-06-29 15:04:42",
      "snippet": "获取配套商机，在线申请采购项目 完善公司资料，让采购商深入了解我的生产能力 一家成立近十年的自动驾驶公司，在IPO时吸引了14家基石投资者认购近一半的发行股份，其中不乏奔驰、比亚迪、GIC、贝莱德等知名机构。这家公司就是Momenta，被市场贴上物理AI第一股的标签，计划于7月8日正式登陆港交所。 它究竟有何魔力，让产业资本与主权基金争相下注？ 根据港交所披露，Momenta于6月29日起招股，至7月3日结束，拟全球发售约1993.83万股，发行价每股295.6港元，募资规模约58.9亿港元（未计超额配股权）。若上市成功，Momenta将成为港股物理AI赛道的重要标杆。 此次IPO最引人注目的莫过于基石投资者阵容。14家机构合计认购约3.76亿美元，占全球发售股份的约49.95%。 产业端，梅赛德斯-奔驰认购2500万美元，比亚迪认购1500万美元——两家车企既是老股东，也是深度合作伙伴，早在2017年便已投资布局。兆易创新认购600万美元。 主权基金与长线资金方面，新加坡政府投资公司（GIC）与富达国际分别以1亿美元领投，贝莱德、橡树资本、富兰克林邓普顿等国际资管机构跟投。中资机构中，高毅资产、博裕资本、华夏基金等各认购1000万美元。 基石阵容的“含金量”不言自明，而Momenta的财务数据同样呈现出强劲的增长势头。2023年至2025年，公司营收从7.43亿元增至24.13亿元，年均复合增长率超过80%；其中许可收入从0.23亿元飙升至9.68亿元，三年增长约42倍，成为增速最快的收入板块。 整体毛利率从17.5%跃升至71.6%，表明其技术授权和解决方案的溢价能力在持续增强。截至2025年底，公司现金储备超过100亿元，资金储备充裕。 进一步看，经调整后的经营利润指标连续改善，研发效率与规模化效应逐步显现。这主要得益于量产车方案的大规模交付，搭载Momenta智驾系统的车辆已超90万辆，数据回流带来的算法迭代速度显著加快，单位成本随之下降。可以说，Momenta正从投入期稳步迈入收获期，营收结构与毛利水平已为其长期盈利奠定坚实基础。 IPO募资净额约56.15亿港元，其中60%投向核心技术研发，包括世界模型迭代、AI算力平台及数据闭环工具链；20%用于Robotaxi商业化落地；10%用于量产车业务拓展；10%作为营运资金。 这意味着上市后公司将继续保持研发投入强度，同时加速商业变现，进一步巩固其在物理AI赛道上的先发优势。 从量产到Robotaxi，Momenta的十年积累 回到业务本身，Momenta的模式被外界概括为一个飞轮，两条腿。 飞轮指通过量产车数据驱动算法迭代——搭载智驾方案的车辆在真实路况中积累海量数据，反哺算法优化；两条腿则对应两条变现路径：一条是为量产车型提供L2+级辅助驾驶解决方案，另一条是布局L4级可规模化无人驾驶出行与物流服",
      "image": "",
      "source": "gasgoo",
      "source_name": "盖世汽车",
      "crawled_at": "2026-06-30T10:31:59.098295+00:00",
      "item_id": "c4959e17a5098df8",
      "publish_ts": 1782716682.0,
      "publish_date": "2026-06-29",
      "image_status": "rejected",
      "image_reason": "同一图片被超过 3 篇文章复用，按站点装饰图处理",
      "category": "市场",
      "brands": [
        "比亚迪",
        "奔驰"
      ],
      "importance": 53,
      "summary": "自动驾驶公司Momenta计划于7月8日登陆港交所，6月29日至7月3日招股，拟全球发售约1993.83万股，发行价每股295.6港元，募资约58.9亿港元。14家基石投资者合计认购约3.76亿美元，占发售股份约49.95%，包括奔驰、比亚迪、GIC、富达国际、贝莱德等。公司2023至2025年营收由7.43亿元增至24.13亿元，搭载其智驾系统车辆已超90万辆。",
      "takeaway": "基石阵容显示车企与长线资金正在押注量产数据驱动的智驾飞轮。",
      "enriched_by": "codex",
      "is_featured": true,
      "has_time": true
    },
    {
      "title": "纵横G700开启OTA升级！越野专属功能定向提升！",
      "url": "https://www.autohome.com.cn/news/202606/1315370.html",
      "publish_time": "2026-06-29 14:59",
      "snippet": "",
      "image": "https://www2.autoimg.cn/chejiahaodfs/g34/M0B/E1/E8/400x300_0_autohomecar__ChxpV2pCFbWAVoADAAxe1L05vAk259.png",
      "source": "autohome",
      "source_name": "汽车之家",
      "crawled_at": "2026-06-30T10:31:31.860659+00:00",
      "item_id": "d0572402843cf41f",
      "publish_ts": 1782716340.0,
      "publish_date": "2026-06-29",
      "image_status": "ok",
      "image_reason": "高置信正文图",
      "category": "技术",
      "brands": [],
      "importance": 10,
      "summary": "",
      "takeaway": "",
      "enriched_by": "rule",
      "is_featured": false,
      "has_time": true
    },
    {
      "title": "延续家族式设计 吉利星瑞L90内饰谍照曝光 看齐新能源车型",
      "url": "https://www.autohome.com.cn/news/202606/1315369.html",
      "publish_time": "2026-06-29 14:58",
      "snippet": "",
      "image": "https://img3.autoimg.cn/chejiahaodfs/g34/M08/DD/16/400x300_0_autohomecar__ChtpWGpB512AH4hPAA54k8ShOdI580.jpg",
      "source": "autohome",
      "source_name": "汽车之家",
      "crawled_at": "2026-06-30T10:31:31.860659+00:00",
      "item_id": "fd00c02be00aa1d1",
      "publish_ts": 1782716280.0,
      "publish_date": "2026-06-29",
      "image_status": "ok",
      "image_reason": "高置信正文图",
      "category": "产品",
      "brands": [
        "吉利"
      ],
      "importance": 14,
      "summary": "",
      "takeaway": "",
      "enriched_by": "rule",
      "is_featured": false,
      "has_time": true
    },
    {
      "title": "纯电三刀砍下去，销量暴跌28%，增程车“流量密码”失效了？",
      "url": "https://www.autohome.com.cn/news/202606/1315367.html",
      "publish_time": "2026-06-29 14:39",
      "snippet": "",
      "image": "https://www2.autoimg.cn/chejiahaodfs/g34/M09/DF/2D/400x300_0_autohomecar__ChtpWGpCEVaAeFYHABAu-9feN-4166.png",
      "source": "autohome",
      "source_name": "汽车之家",
      "crawled_at": "2026-06-30T10:31:31.860659+00:00",
      "item_id": "f49a4ea9a4ba042b",
      "publish_ts": 1782715140.0,
      "publish_date": "2026-06-29",
      "image_status": "ok",
      "image_reason": "高置信正文图",
      "category": "技术",
      "brands": [],
      "importance": 17,
      "summary": "",
      "takeaway": "",
      "enriched_by": "rule",
      "is_featured": false,
      "has_time": true
    },
    {
      "title": "广汽集团29周年际累计产销将破3000万辆",
      "url": "https://auto.gasgoo.com/news/202606/29I70463624C109.shtml",
      "publish_time": "2026-06-29 14:38:04",
      "snippet": "获取配套商机，在线申请采购项目 完善公司资料，让采购商深入了解我的生产能力 盖世汽车获悉 据广汽集团公布，今年1至5月累计销量约62.82万辆，同比增长3.80%，5月单月销量达12.73万辆，同比增长8.18%。其中，基于新流程体系开发的埃安i60月销已破万辆，与华为联创的启境GT7如期上市，广汽丰田铂智系列亦保持热销。 广汽集团计划于7月16日举办3000万用户感恩活动，届时将安排第3000万辆整车下线，并同步启动用户故事征集，邀请车主分享用车经历。 在品质管控环节，广汽搭建了“五高一山一尘”全域验证体系，新车需经历高温、高寒、复杂路况等测试，核心部件经过耐久强化检验；同时依托AI视觉检测系统对车身漆面与零部件装配实施全数检测，以此作为出厂标准。 回顾发展，广汽集团于1997年成立，初期以“小规模起步、滚动发展”模式起步，年产量不足万辆，现已形成自主与合资并进、七大板块协同的格局，年产销突破200万辆，连续十三年位列《财富》世界500强，累计工业总产值近5万亿元。 面对行业转型，广汽于2024年启动“番禺行动”，推动总部下沉，整合研发、生产、供应链与销售，建立一体化运营平台，并引入DSTE、IPD、IPMS、ITR等管理流程，设立市场化前线单元，以缩短新车开发周期和服务响应时间。 广汽集团表示，后续将继续推进改革，保持核心技术投入，以产品和服务回应市场需求。6月28日恰逢广汽成立29周年，累计产销即将跨越3000万辆，这一数字背后是3000万个家庭的出行日常，亦是企业持续运营的积累。 本文地址：http://auto.gasgoo.com/News/2019/05/300656465646I70107904C601.shtml 本文地址：https://auto.gasgoo.com/news/202606/29I70463624C109.shtml 联系邮箱：info@gasgoo.com 求职应聘：021-39197800-8035 简历投递：zhaopin@gasgoo.com 客服微信：gasgoo12 (豆豆) 新闻热线：021-39586122 商务合作：021-39586681 市场合作：021-39197800-8032 研究院项目咨询：021-39197921 盖世汽车社区 盖世大学堂-公开课 英文资讯站 热门内容 数据报告 盖世汽车产业大数据",
      "image": "https://imagecn.gasgoo.com/moblogo/News/160_110/2026/6/3012042689.jpg",
      "source": "gasgoo",
      "source_name": "盖世汽车",
      "crawled_at": "2026-06-30T10:31:59.098295+00:00",
      "item_id": "ac815e50473899db",
      "publish_ts": 1782715084.0,
      "publish_date": "2026-06-29",
      "image_status": "ok",
      "image_reason": "高置信正文图",
      "category": "市场",
      "brands": [
        "埃安",
        "丰田",
        "广汽"
      ],
      "importance": 43,
      "summary": "广汽集团披露，今年1至5月累计销量约62.82万辆，同比增长3.80%；5月销量12.73万辆，同比增长8.18%，埃安i60月销已破万辆，与华为联创的启境GT7如期上市。集团计划7月16日举办3000万用户感恩活动，安排第3000万辆整车下线并启动车主故事征集。广汽1997年成立，如今年产销突破200万辆，累计工业总产值近5万亿元，并以“五高一山一尘”验证体系强化品质管控。",
      "takeaway": "3000万辆节点背后，广汽下一阶段压力转向组织效率和新品转化。",
      "enriched_by": "codex",
      "is_featured": true,
      "has_time": true
    },
    {
      "title": "为家庭探索而生！全新猛士M817正式上市",
      "url": "https://www.iautodaily.com/news/brand/weijiatingtansuoershengquanxinmengshim817zhengshishangshi/",
      "publish_time": "2026-06-29 14:04:12",
      "snippet": "从城市通勤到山海穿越，全新猛士M817装下全家出行向往。 越野新生活，探享新境界！6月27日，猛士汽车重磅年度车型——全新猛士M817在武汉正式上市。承袭57年军工越野基因，联合华为乾崑最强智能科技，一举打破“越野、舒适、智能”的行业不可能三角，将全场景越野性能、顶尖智能与百万级舒享体验完美融合，为中国家庭打造兼顾城市通勤与山野探索的全能家庭“卫士”，正式开启“人人可享”的越野新生活。 一台车装下全家向往，解锁全场景出行新范式 一千个家庭，有一千种出行向往。五天工作日，需要体面高效的通勤代步；两天周末，想带孩子奔赴近郊触摸自然；七天小长假，渴望携全家穿越独库公路、川西高原，看雪山星河。全新猛士M817精准锚定家庭用户全场景出行需求，让城市烟火与山野自由无缝衔接。 通勤场景下，新车搭载越野第一的62.5度电池包，带来同级第一的301km CLTC纯电续航，城市通勤一周一充即可，完全可当纯电车使用；800V高压平台搭配6C超充电池，30%-80% 充电不到10分钟，在服务区伸个懒腰、买一杯咖啡的时间就能满电出发。CLTC综合续航高达1450km，长途穿越无需频繁补能；馈电油耗低至百公里6.99L，媲美家用代步轿车，大幅降低家庭用车成本。 家庭出行的空间需求，也由“移动大平层”座舱完美解决。依托3005mm超长轴距，后排座椅放倒即可形成2.1米纯平舒享大床，孩子能肆意打滚，大人可舒展休憩；828L常规后备厢可同时放下12个20寸行李箱、1个28寸行李箱和1个手提旅行包，二排座椅放倒后容积拓展至2112L，高尔夫球包、冲浪板、山地车等大件装备轻松收纳，全家出行的行李与热爱一车装下。 越野从来不是专业玩家的专属，更该是全家共享的乐趣。全新猛士M817以赛级同源的硬核实力，从专业爱好到人人可享，大大降低越野门槛，让新手也能带着家人从容征服山海。 新车搭载的2.0T极猛动力，完成43项技术升级，拥有9项同级第一。2.0T混动专用发动机搭配前后双电机，综合功率达715kW，轮边最大扭矩13685N·m，动力远超6.0T燃油发动机，通过了“高原动力之星”和“中国心”十佳发动机及混动系统认证，成为行业里首个获得行业权威“双认证”的系统。作为行业唯一实现全场景不掉电的越野车，同级第一110kW额定发电功率，搭配3kW超大功率高压风扇，实现高速161km/h全程稳定不掉电，极限工况动力不打折。 猛士智能全地形系统让越野变成人人可享的生活方式。猛士智能E锁具备锁止快、分配准、脱困轻松三大特色，配合全新开发的电机瞬态变化率控制系统，能实现全速域防滑，毫秒级响应，起步不打滑，行驶不跑偏。9种驾驶模式一键切换，1键智能AUTO模式可自动适配各种复杂路况，让越野新手也能轻松拥有越野老炮般的实力。行业最强蠕行模式搭配900mm涉水深度、3.5m最小原地掉头半径，无论是陡坡攀爬、泥泞脱困还是溪流",
      "image": "https://www.iautodaily.com/wp-content/uploads/2026/06/1_-480x320.png",
      "source": "iautodaily",
      "source_name": "汽车公社",
      "crawled_at": "2026-06-30T10:30:31.771201+00:00",
      "item_id": "85ce275a5dbf1a72",
      "publish_ts": 1782713052.0,
      "publish_date": "2026-06-29",
      "image_status": "ok",
      "image_reason": "高置信正文图",
      "category": "技术",
      "brands": [],
      "importance": 27,
      "summary": "",
      "takeaway": "",
      "enriched_by": "rule",
      "is_featured": false,
      "has_time": true
    },
    {
      "title": "29.99万元起售，全新猛士M817正式上市，更懂中国家庭的智野“卫士”",
      "url": "https://www.iautodaily.com/news/brand/2999wanyuanqishouquanxinmengshim817zhengshishangshigengdongz/",
      "publish_time": "2026-06-29 14:00:57",
      "snippet": "打破行业越野、舒适、智能“不可能三角”。 智野新生，探享新境！6月27日，以“探享新境界”为主题，猛士汽车联合华为乾崑深度共创的“豪华智能越野SUV”——全新猛士M817正式上市。新车推出Mate、Mate+、Max、Max+、Ultra五款配置版本，官方指导价29.99万-39.99万元，即刻下订，尊享五类超值权益，总价值最高6.5万元。 当下的汽车市场，在高端越野领域，极致越野性能、全域高阶智能、全家舒适驾乘三者始终难以兼顾，成为行业公认的“不可能三角”。全新猛士M817承袭57年军工越野基因，顺应新时代家庭出行之需，以中国最强越野实力，联合华为乾崑最强智能科技，打破行业“不可能三角”，将全场景越野性能、顶尖智能与舒适体验融为一体，开启智能越野新生活。新车全方位适配“5+2+X”多元出行需求，即“5天城市通勤、2天近郊野奢、X次随心远征”的越野新生活，既是一台征服山海的越野座驾，更是为万千中国家庭打造的家庭“卫士”。 雄魂美学全面进阶，树立中国原创美学新标杆 只有原创的设计，才有独立的灵魂。全新猛士M817秉持“用猛士设计，讲好中国故事”的初心，坚持原创造型设计，吸纳九州山河气韵，融汇东方醒狮力量，古今意象相融，勾勒独树一帜的东方越野意境。 全新猛士M817实现雄魂美学全面进阶。承袭军工铁骨根基，塑造醒狮雄健体态，前大灯设计，形为止戈，“意”在守护，搭配越王勾践剑的菱形花纹，传递止戈为武的东方哲学；尾部以古代利剑出鞘之时的形态为设计灵感，形为利刃，“意”在藏锋，塑造剑指苍穹后尾灯。新车外观设计，用极简姿态传递“不怒自威”的气势，树立中国豪华越野原创美学新标杆。 线条勾勒风骨，色彩赋予灵魂。全新猛士M817车身色彩以华夏山河为灵感，外观提供格宗黑、玉龙银、鸣沙黄、秦岭绿、昆仑白、乌兰橙六款色彩，新车色乌兰橙复刻了乌兰哈达火山群特有的炽烈色调，流光幻彩一眼入魂。搭配全新的20英寸六辐双刃造型轮毂，尽显硬派越野的力量姿态。内饰从山水意境中汲取灵感，打造迎松墨、丹霞棕、锦川红、霞影橙四款内饰色彩，全新内饰配色霞影橙，灵感源于王勃《滕王阁序》中“落霞与孤鹜齐飞”，橙黑撞色兼顾都市雅致与旷野激情。行走都市，藏锋于内；奔赴山海，傲然于外，全新猛士M817就是中国原创设计力量崛起的新范本。 环塔验证全域越野实力，确立新能源性能新典范 以赛道的极限，标定产品的底线。强悍的越野性能是打破“不可能三角”的第一重核心底气。基于全新猛士M817核心技术平台打造的原厂战车，征战2026环塔拉力赛，7500公里总里程，历经沙漠、戈壁、刀锋沙丘全场景极限考验，强势斩获两冠一亚，更成为SS5、SS6“双魔鬼赛段”唯一100%完赛车队，以赛场极限淬炼，验证猛士军工品质的含金量。 新车搭载的2.0T极猛动力，完成43项技术升级，拥有9项同级第一。混动专用2.0T发动机，通过“高原动力之星”与",
      "image": "https://www.iautodaily.com/wp-content/uploads/2026/06/1cada705b1cc61ec6d582d261e69b2a7-480x320.jpeg",
      "source": "iautodaily",
      "source_name": "汽车公社",
      "crawled_at": "2026-06-30T10:30:31.771201+00:00",
      "item_id": "22ab1c845881cdb1",
      "publish_ts": 1782712857.0,
      "publish_date": "2026-06-29",
      "image_status": "ok",
      "image_reason": "高置信正文图",
      "category": "产品",
      "brands": [],
      "importance": 20,
      "summary": "",
      "takeaway": "",
      "enriched_by": "rule",
      "is_featured": false,
      "has_time": true
    },
    {
      "title": "零百加速时间最快6.6秒 小鹏正式公布MONA L03动力信息",
      "url": "https://www.autohome.com.cn/news/202606/1315365.html",
      "publish_time": "2026-06-29 13:39",
      "snippet": "",
      "image": "https://img3.autoimg.cn/chejiahaodfs/g33/M01/E0/27/400x300_0_autohomecar__Chto52pB8NeAbCDLAApRaYbvcms832.png",
      "source": "autohome",
      "source_name": "汽车之家",
      "crawled_at": "2026-06-30T10:31:31.860659+00:00",
      "item_id": "2e9e202a352bca16",
      "publish_ts": 1782711540.0,
      "publish_date": "2026-06-29",
      "image_status": "ok",
      "image_reason": "高置信正文图",
      "category": "市场",
      "brands": [
        "小鹏"
      ],
      "importance": 14,
      "summary": "",
      "takeaway": "",
      "enriched_by": "rule",
      "is_featured": false,
      "has_time": true
    },
    {
      "title": "半年五轮融资，德塔智能什么来头？",
      "url": "https://auto.gasgoo.com/news/202606/29I70463618C601.shtml",
      "publish_time": "2026-06-29 12:25:50",
      "snippet": "获取配套商机，在线申请采购项目 完善公司资料，让采购商深入了解我的生产能力 盖世汽车获悉，德塔智能（Delta Intelligence）已于近日连续完成种子+轮、天使轮及天使+轮融资。 其中，种子+轮由元禾控股和复星锐正共同投资；天使轮由华映资本、华盖资本、联想创投联合领投，老股东元禾控股、复星锐正超额追投；天使+轮获得珠海科技产业集团、海望资本、梅花创投等财务投资机构支持，半导体产业方交源资产及某汽车产业方深度参与，老股东华映资本继续加注。 加上此前北京通研院、乐聚智能、智元创新、星海图和高瓴创投参与的两轮融资，德塔智能在成立不到半年的时间内已连续完成五轮融资。 德塔智能成立于2026 年 1 月，公司孵化自北京通用人工智能研究院，具备从基础模型、系统架构到落地交付的完整能力闭环。 其中，德塔智能创始人兼CEO马晓健，曾在Google Robotics、NVIDIA Research 工作并长期从事大规模机器学习与具身智能基础模型等前沿研究。 联合创始人刘航欣现任北京大学助理教授，曾深度参与美国DARPA、ONR、NSF机器人项目，回国后在通研院牵头完成多项人形机器人工业与特种场景中的应用交付。 另一联合创始人兼首席科学家黄思远，现任北京通用人工智能研究院具身机器人中心主任，曾在DeepMind、Meta从事前沿研究。 在核心业务上，德塔智能专注于原生人形机器人基础模型的研发，以自主3D世界引擎为核心，推动人形机器人从“分散能力”到“全身协同”的进化，最终实现通用的全身协同操作。 德塔智能研发的人形机器人基础模型，聚焦把人形机器人的完整身体作为建模对象，围绕 Loco-manipulation 构建从 3D 场景理解、任务推理、全身控制到力位交互的模型闭环，让机器人在理解任务的同时，也能知道身体该如何配合完成任务。 目前，德塔智能正在持续迭代人形机器人基础模型核心架构，并在宇树、智元、乐聚等多类人形机器人本体上完成跨本体适配与性能验证。 围绕工业制造与能源等场景，德塔团队已经完成了一汽红旗产线协作、南方电网配电站巡检、SMT 料盘分拣等真实任务验证，并在任务成功率、连续作业时长及跨场景泛化能力上取得阶段性进展。 最终，德塔智能的目标是，在不同人形机器人本体上提供可迁移、可泛化的人形机器人基础模型，并通过与本体厂商的联合验证，缩短技术从模型训练走向真实场景的路径。 盖世汽车《Seeds 发现》栏目，旨在打造一个链接初创企业、产业链生态合作伙伴以及投资机构、地方政府的服务平台，为产业链上下游深度赋能。该栏目自启动以来，一直致力于发掘智能化变革大潮中对行业具有重要启发和引领作用的好公司、好技术、好的商业模式，推动汽车产业创新力量的成长。据盖世汽车统计，经《Seeds 发现》栏目报道过的初创公司，几乎所有都已经成功对接了产业链生态资源。 本文地址：http://",
      "image": "https://imagecn.gasgoo.com/moblogo/News/160_110/2026/6/2912254901.jpg",
      "source": "gasgoo",
      "source_name": "盖世汽车",
      "crawled_at": "2026-06-30T10:31:59.098295+00:00",
      "item_id": "4d9eeabf23c73d6d",
      "publish_ts": 1782707150.0,
      "publish_date": "2026-06-29",
      "image_status": "ok",
      "image_reason": "高置信正文图",
      "category": "市场",
      "brands": [
        "一汽",
        "红旗"
      ],
      "importance": 39,
      "summary": "德塔智能近日连续完成种子+轮、天使轮和天使+轮融资，加上此前两轮，成立不到半年已完成五轮融资。公司2026年1月成立，孵化自北京通用人工智能研究院，创始团队成员曾在Google Robotics、NVIDIA Research、DeepMind、Meta及通研院从事机器人研究。德塔聚焦原生人形机器人基础模型，已在宇树、智元、乐聚等本体上验证，并完成一汽红旗产线协作、南方电网巡检、SMT料盘分拣等任务。",
      "takeaway": "资本密集下注说明人形机器人基础模型正从论文能力转向场景验证。",
      "enriched_by": "codex",
      "is_featured": true,
      "has_time": true
    },
    {
      "title": "华为途灵平台，赋能汽车底盘“智商”？",
      "url": "https://auto.gasgoo.com/news/202606/29I70463617C103.shtml",
      "publish_time": "2026-06-29 12:14:53",
      "snippet": "获取配套商机，在线申请采购项目 完善公司资料，让采购商深入了解我的生产能力 2026年6月26日，鸿蒙智行TECH DAY——华为途灵平台技术专场在上海举行。这是华为首度针对其底盘技术进行系统性拆解。随着新能源汽车行业进入下半场，整车智能的竞争焦点正在从单一的智能座舱、辅助驾驶，向更底层的底盘架构延伸。 传统汽车工业中，底盘性能的上限往往由机械硬件的规格决定。而华为途灵平台呈现出一种截然不同的思路：通过算力、通信架构与AI算法的深度介入，将底盘从被动执行的机械部件转化为具备“感知、思考、执行”能力的智能化系统。 传统底盘由驱动、制动、转向、悬架等各自独立的电子控制单元分别控制，这种分布式架构导致各部件难以形成合力。 华为途灵平台的核心变革在于“控制上移与全维协同”——依托华为数字底盘引擎，实现了驱动、制动、悬架、转向、车身、热管理六大控制域的融合。端到端调度能力较传统方案提升10倍以上，最小决策链路时延低至1毫秒。 这种能力建立在华为在计算与通信领域的底层技术积累之上。 在算力层面，途灵平台通过三级缓存架构减少数据在总内存中的排队时间，缓解运算拥堵；硬件级“零值过滤器”可在计算前自动剔除无效数据，提升运算效率；多精度并行计算则改变了行业单线串行计算的耗时问题。 在通信层面，华为为底盘开辟了专属“VIP数据专线”，确保打滑、爆胎等关键控制指令优先传输。途灵平台能够实现每秒100次打滑计算，并在2毫秒内完成全链路的识别与响应。 这一技术路径的可行性已在实践中得到验证。 2025年，搭载华为途灵平台的智界R7参与了中国汽研发起的“智能底盘先锋计划”测评，获评“标杆车型”。智界R7在麋鹿测试中跑出82.3公里/小时的成绩。 途灵平台带来的改变最终落在三个维度：易操控、更舒适、超安全。 在易操控方面，途灵平台通过扭矩毫秒级的前后轮分配，解决了入弯推头和出弯甩尾两大操控痛点。5.48米长的尊界S800凭借大角度后轮转向等技术，最小转弯半径仅为5.05米。 在舒适性方面，途灵平台通过底盘系统与智驾系统的跨域协同，复用ADS传感器实现路面预瞄，提前调整悬架阻尼。针对电动车常见的晕车问题，途灵平台综合协同驱动、制动、转向、悬架多维度进行系统化抑制。在实际使用中，华为途灵平台累计激活晕车舒缓功能达103.4万次。 在安全层面，途灵平台通过融合轮端电机旋变、胎压传感器、轮速传感器等多源数据，可在爆胎瞬间以比人类快5倍以上的速度完成识别与响应。 值得一提的是，途灵平台在智驾状态下发生爆胎时，智驾系统可直接接管车辆而不退出。此外，搭载在尊界S800 Grand Design典藏大观上的全新一代途灵龙行平台，采用800V全主动悬架架构，单轮最大举升力超过12千牛。其首发搭载的全域融合架构2.0，路况感知识别准确率提高50%，时延降低50%。主动悬架还开发了全向预抬升功能——碰撞不可避免",
      "image": "https://imagecn.gasgoo.com/moblogo/News/160_110/2026/6/1809280629.jpg",
      "source": "gasgoo",
      "source_name": "盖世汽车",
      "crawled_at": "2026-06-30T10:31:59.098295+00:00",
      "item_id": "f50a7c1e7d792671",
      "publish_ts": 1782706493.0,
      "publish_date": "2026-06-29",
      "image_status": "ok",
      "image_reason": "高置信正文图",
      "category": "技术",
      "brands": [],
      "importance": 31,
      "summary": "2026年6月26日，鸿蒙智行TECH DAY华为途灵平台技术专场在上海举行，华为首次系统拆解底盘技术。途灵平台通过数字底盘引擎融合驱动、制动、悬架、转向、车身、热管理六大控制域，端到端调度能力较传统方案提升10倍以上，最小决策链路时延低至1毫秒。平台可每秒完成100次打滑计算，并在2毫秒内识别与响应；搭载车型智界R7曾获评智能底盘标杆车型，麋鹿测试成绩为82.3公里/小时。",
      "takeaway": "底盘智能化把竞争从硬件规格推向跨域控制和软件调校能力。",
      "enriched_by": "codex",
      "is_featured": true,
      "has_time": true
    },
    {
      "title": "纬钛机器人再获新融资",
      "url": "https://auto.gasgoo.com/news/202606/29I70463616C601.shtml",
      "publish_time": "2026-06-29 12:06:49",
      "snippet": "获取配套商机，在线申请采购项目 完善公司资料，让采购商深入了解我的生产能力 盖世汽车获悉，上海纬钛科技有限公司（简称“纬钛机器人”，ViTai Robotics）已于近日完成Pre-A轮融资。本轮融资由红鸟启航基金领投，领屹投资、永鑫方舟、韦豪创芯、宁波吉德等联合参投，上海天使会联合投资，多家老股东继续加持。 官方指出，本轮融资所募集的资金将投向三个方向： 第一，视触觉感知技术的持续迭代，包括在传感器的小型化、分辨率、采样频率和感知精度等方面继续精进，并进一步提升批量生产与规模化落地的能力； 第二，执行器的产品落地，涵盖夹爪、灵巧手等末端执行器产品，以及围绕执行器构建的手眼协同算法、力控策略和面向真实场景的操作能力； 第三，视触觉数据采集系统与模型闭环的推进，让机器人不仅能在大量视觉数据中学习“看到”，更能在真实的接触数据中学会“碰到之后怎么做”。 与此同时，纬钛机器人也将重点引入视触觉感知、执行器落地、数采与模型闭环三大方向的技术人才，同时补充生产制造与量产交付方面的力量。 这是纬钛机器人近一年里完成的第三轮融资，累计融资数亿元：天使轮由小米战投领投，宽桥恒松、雅瑞资本、梅花创投、微光创投、iCANX Fund等跟投；天使+轮由顶级美元VC祥峰投资领投，雅瑞资本、梅花创投、微光创投、iCANX Fund等多家老股东参投。更早的种子轮中，纬钛机器人还曾获得多个AI行业领袖的投资。 特别值得关注的是，除了资金，小米在智能制造、消费电子、供应链管理和产品工程化方面的深厚积累，也为纬钛机器人提供了一个将实验室能力置于真实产业标准下反复打磨的环境。去年，小米还通过旗下瀚星创投追加投资，双方的合作关系不断加深。 据悉，纬钛机器人也是小米战投在2025年投出的第一家具身智能企业。 纬钛机器人起源于MIT计算机科学与人工智能实验室，创始人李瑞自2005年便开始机器人和计算机视觉等领域的研究，在MIT读博期间师从美国两院院士Edward Adelson教授，共同开创并引领了视触觉研究路线。 回国后，李瑞将视触觉感知技术从基础研究一路推进至产业化阶段，并已首家实现量产。目前，纬钛机器人已经打造了一套从视触觉感知，到执行器落地，再到视触觉数据采集与模型闭环的完整技术体系，并已与3C、汽车、家电、新能源等领域的众多头部企业达成合作，应用覆盖精准放置与装配、无序自适应抓取、柔性物体操作等众多场景。 2026年，将是纬钛机器人从产品交付走向规模化落地的关键一年。 目前，纬钛机器人的产品销售大致分为三类客户群：以小米为代表的工业场景客户，在真实产线上进行精细化操作的落地应用；具身智能机器人公司，采购两指和五指视触觉传感器用于夹爪和灵巧手的研发与集成；以及来自科研机构和模型团队的视触觉数采设备需求。 其中，纬钛机器人的视触觉传感器的产业价值，正在被头部客户快速验证。在消费电子制造领域，小",
      "image": "https://imagecn.gasgoo.com/moblogo/News/160_110/2026/6/2912064749.jpg",
      "source": "gasgoo",
      "source_name": "盖世汽车",
      "crawled_at": "2026-06-30T10:31:59.098295+00:00",
      "item_id": "fcab6e3c0fdad9a8",
      "publish_ts": 1782706009.0,
      "publish_date": "2026-06-29",
      "image_status": "ok",
      "image_reason": "高置信正文图",
      "category": "市场",
      "brands": [
        "小米"
      ],
      "importance": 35,
      "summary": "上海纬钛科技有限公司近日完成Pre-A轮融资，由红鸟启航基金领投，领屹投资、永鑫方舟、韦豪创芯、宁波吉德等参投，老股东继续加持。本轮资金将用于视触觉感知技术迭代、夹爪和灵巧手等执行器产品落地，以及视触觉数据采集系统与模型闭环建设。纬钛近一年已完成第三轮融资，累计数亿元，小米战投曾领投天使轮，并通过瀚星创投追加投资。公司技术源自MIT视触觉研究路线，已在3C、汽车、家电和新能源场景合作落地。",
      "takeaway": "视触觉融资升温，反映机器人产业正补齐从看见到会操作的短板。",
      "enriched_by": "codex",
      "is_featured": true,
      "has_time": true
    },
    {
      "title": "王朝网旗舰大型车 一眼高级感 比亚迪大汉实车曝光 插混+纯电",
      "url": "https://www.autohome.com.cn/news/202606/1315363.html",
      "publish_time": "2026-06-29 12:03",
      "snippet": "",
      "image": "https://img3.autoimg.cn/chejiahaodfs/g33/M02/DF/A3/400x300_0_autohomecar__Chto52pB6NmAJdATAAhDZjBj4cA116.jpg",
      "source": "autohome",
      "source_name": "汽车之家",
      "crawled_at": "2026-06-30T10:31:31.860659+00:00",
      "item_id": "3cca180dca81c1aa",
      "publish_ts": 1782705780.0,
      "publish_date": "2026-06-29",
      "image_status": "ok",
      "image_reason": "高置信正文图",
      "category": "技术",
      "brands": [
        "比亚迪"
      ],
      "importance": 14,
      "summary": "",
      "takeaway": "",
      "enriched_by": "rule",
      "is_featured": false,
      "has_time": true
    },
    {
      "title": "晓莺说｜摩洛哥现场观察（1）：雷诺RG如何用好中国能力",
      "url": "https://auto.gasgoo.com/news/202606/30I70463610C108.shtml",
      "publish_time": "2026-06-29 11:49:11",
      "snippet": "获取配套商机，在线申请采购项目 完善公司资料，让采购商深入了解我的生产能力 这次受雷诺集团邀请，参加2026 Tech World Tour Morocco，来到了雷诺位于摩洛哥丹吉尔的工厂、低碳制造现场、当地供应链企业SNOP、Tanger Med地中海港口综合体参访学习，受益匪浅。作为一家非典型欧洲车企，雷诺正在快速重新组织全球资源，尤其是把中国汽车产业能力，转化为其全球竞争力。 雷诺在摩洛哥的工业布局始于1928年，目前摩洛哥已成为雷诺集团全球第二大生产国，2025年产量超过39万辆，其中丹吉尔工厂产量接近30万辆，是一个高度以出口为导向的全球制造节点。 雷诺的丹吉尔工厂，并不是现在在中国常见的那种用极高自动化率、密集机器人、数字化看板来制造震撼感的现代工厂，而是另一套更务实的工业逻辑：高产能利用率、稳定生产节奏、高出口比例、低碳运营体系、顺畅物流网络，以及围绕整车制造形成的完整生态。 在丹吉尔工厂，车辆下线之后，可以通过顺畅的铁路和物流体系进入Tanger Med港口，再装船远销欧洲及全球市场。工厂、铁路、港口、自由区、供应商网络之间的距离被大幅压缩，制造、物流和出口不再是分散环节，而是被整合成一个工厂、港口、铁路、供应商、低碳的高效率闭环协同系统，这也是雷诺集团在欧洲之外最重要的布局之一。 随着全球地缘政治的复杂多变，汽车产业加速向属地化（Region for Region）进行分化。摩洛哥近几年的战略价值持续攀升，在于它提供了一种特殊平衡：它不在欧洲本土，却离欧洲足够近；它成本更有弹性，却不远离目标市场；它有港口和铁路基础设施，又具备整车制造和供应链生态；它能够服务欧洲，也能辐射更广阔的国际市场。 尤其是Tanger Med地中海港口综合体的发展，形成了港口、物流和工业平台的有效组合体。对汽车产业而言，港口不是配套设施，而是制造体系的一部分。一辆车从工厂下线，并不意味着价值链结束。它还要进入物流系统，进入港口，进入船运网络，最终抵达欧洲和全球市场。 丹吉尔的竞争力，不只是“有比欧洲更便宜的工厂”，而是“工厂+港口+铁路+自由区+供应商+物流”的综合能力组合。 同时，雷诺在摩洛哥特别强调低碳制造。丹吉尔工厂使用超过90%的可再生能源，并采用零工业液体排放模式。这不是纸面上的ESG，而是欧洲车企海外制造基地未来必须回答的问题：如何在成本、效率、碳足迹、供应链透明度和法规适配之间取得平衡。这也是特别值得中国企业注意的地方，要进入欧洲等高地市场，ESG绝对不能只停留在口号上，必须深入实践。 作为雷诺在欧洲之外最重要的南岸制造平台，摩洛哥解决了雷诺在全球竞争中的核心问题：在哪里制造，才能兼顾成本、效率、低碳和市场距离？ futuREady：雷诺如何重组全球资源 雷诺正在从Renaulution进入futuREady。如果说Renaulution帮助雷诺完成",
      "image": "https://imagecn.gasgoo.com/moblogo/News/160_110/2026/6/2911485245.jpg",
      "source": "gasgoo",
      "source_name": "盖世汽车",
      "crawled_at": "2026-06-30T10:31:59.098295+00:00",
      "item_id": "a89d25e8f02c2b92",
      "publish_ts": 1782704951.0,
      "publish_date": "2026-06-29",
      "image_status": "ok",
      "image_reason": "高置信正文图",
      "category": "市场",
      "brands": [
        "现代"
      ],
      "importance": 28,
      "summary": "雷诺在2026 Tech World Tour Morocco中展示其摩洛哥丹吉尔工厂、低碳制造体系、当地供应链企业SNOP及Tanger Med港口综合体。雷诺在摩洛哥的工业布局始于1928年，目前当地已成为集团全球第二大生产国，2025年产量超过39万辆，其中丹吉尔工厂接近30万辆。该基地通过工厂、铁路、港口、自由区、供应商和低碳体系协同，服务欧洲及全球出口。",
      "takeaway": "雷诺摩洛哥样本说明全球化制造竞争正在转向区域闭环能力。",
      "enriched_by": "codex",
      "is_featured": true,
      "has_time": true
    },
    {
      "title": "可选装激光雷达/整体造型与现款一致 新款比亚迪元UP内饰谍照曝光",
      "url": "https://www.autohome.com.cn/news/202606/1315362.html",
      "publish_time": "2026-06-29 11:34",
      "snippet": "",
      "image": "https://www2.autoimg.cn/chejiahaodfs/g34/M0A/DC/D4/400x300_0_autohomecar__ChtpWGpB41CAH0vIABIv2VZOktc290.png",
      "source": "autohome",
      "source_name": "汽车之家",
      "crawled_at": "2026-06-30T10:31:31.860659+00:00",
      "item_id": "5184cfc1dae6b595",
      "publish_ts": 1782704040.0,
      "publish_date": "2026-06-29",
      "image_status": "ok",
      "image_reason": "高置信正文图",
      "category": "产品",
      "brands": [
        "比亚迪"
      ],
      "importance": 14,
      "summary": "",
      "takeaway": "",
      "enriched_by": "rule",
      "is_featured": false,
      "has_time": true
    },
    {
      "title": "四季度开启交付 全新宝马iX3长轴距版将于成都车展开启预售",
      "url": "https://www.autohome.com.cn/news/202606/1315361.html",
      "publish_time": "2026-06-29 11:22",
      "snippet": "",
      "image": "https://www2.autoimg.cn/chejiahaodfs/g33/M0B/DE/A3/400x300_0_autohomecar__ChxpVmpB2FKABX22AAX6VwVtgjs909.png",
      "source": "autohome",
      "source_name": "汽车之家",
      "crawled_at": "2026-06-30T10:31:31.860659+00:00",
      "item_id": "eb92aaf07f5449cf",
      "publish_ts": 1782703320.0,
      "publish_date": "2026-06-29",
      "image_status": "ok",
      "image_reason": "高置信正文图",
      "category": "市场",
      "brands": [
        "宝马"
      ],
      "importance": 28,
      "summary": "",
      "takeaway": "",
      "enriched_by": "rule",
      "is_featured": false,
      "has_time": true
    },
    {
      "title": "方盒子享界G9实车图曝光 增程+纯电 增程版纯电续航最长超400km",
      "url": "https://www.autohome.com.cn/news/202606/1315360.html",
      "publish_time": "2026-06-29 11:20",
      "snippet": "",
      "image": "",
      "source": "autohome",
      "source_name": "汽车之家",
      "crawled_at": "2026-06-30T10:31:31.860659+00:00",
      "item_id": "e5389687e85c33a0",
      "publish_ts": 1782703200.0,
      "publish_date": "2026-06-29",
      "image_status": "rejected",
      "image_reason": "命中头像/站点装饰/广告/占位图规则",
      "category": "技术",
      "brands": [],
      "importance": 10,
      "summary": "",
      "takeaway": "",
      "enriched_by": "rule",
      "is_featured": false,
      "has_time": true
    },
    {
      "title": "东风奕派M8预售订单突破10000台",
      "url": "https://auto.gasgoo.com/news/202606/29I70463609C501.shtml",
      "publish_time": "2026-06-29 11:13:06",
      "snippet": "获取配套商机，在线申请采购项目 完善公司资料，让采购商深入了解我的生产能力 盖世汽车讯 东风奕派官方宣布，奕派M8新车截至6月28日24时，预售订单突破10,000 台。据悉，东风奕派M8已于昨日发布，预售价19.98万元起。 作为东风奕派与华为乾崑战略合作升级后的首款落地车型，奕派M8汇聚东风汽车、华为乾崑、宁德时代三方技术资源，打出“华派黄金标准大六座”的产品定位，并首次完整配备华为乾崑六件套智能方案。 奕派M8采用“风起云展”设计语言，整体姿态舒展大气。车顶首次配备140mm长的智显小蓝灯，两侧后视镜、前大灯组及尾部也分别融入小蓝灯元素，构成全车9个辅助驾驶交互信号灯，在提升科技感的同时，承担着智驾状态的可视化提示功能。 车身尺寸方面，新车车长达到5米级别，轴长比为60.3%，为车内空间布局提供了良好基础。据官方信息，新车将提供5种车身颜色、3种内饰配色及3种轮毂造型供用户选择。 新车将首批搭载华为乾崑智驾ADS 5 Pro，感知硬件共27个，包括业界首创的舱内激光视觉传感器Limera。该传感器体积仅11×3.8cm，集成于挡风玻璃后方，通过“一镜双模”共光路光学架构，同时接收3D点云与2D图像，实现对锥桶、纸箱、水马等异形障碍物的115米外探测，对30cm小目标检测距离较120线激光雷达提升最高43%。 此外，车辆还配备3个4D毫米波雷达、11个高精摄像头和12个超声波雷达。智驾计算基于WEWA2.0架构，云端算力达60EFLOPS，累计训练里程超10亿公里。功能层面，高速NCA平均接管里程超1500公里，城区NCA可应对复杂环岛、窄道会车等路况，园区领航辅助覆盖全国80万个园区及停车场。 本文地址：http://auto.gasgoo.com/News/2019/05/300656465646I70107904C601.shtml 本文地址：https://auto.gasgoo.com/news/202606/29I70463609C501.shtml 联系邮箱：info@gasgoo.com 求职应聘：021-39197800-8035 简历投递：zhaopin@gasgoo.com 客服微信：gasgoo12 (豆豆) 新闻热线：021-39586122 商务合作：021-39586681 市场合作：021-39197800-8032 研究院项目咨询：021-39197921 盖世汽车社区 盖世大学堂-公开课 英文资讯站 热门内容 数据报告 盖世汽车产业大数据",
      "image": "",
      "source": "gasgoo",
      "source_name": "盖世汽车",
      "crawled_at": "2026-06-30T10:31:59.098295+00:00",
      "item_id": "b362694f2e2ad330",
      "publish_ts": 1782702786.0,
      "publish_date": "2026-06-29",
      "image_status": "rejected",
      "image_reason": "同一图片被超过 3 篇文章复用，按站点装饰图处理",
      "category": "产品",
      "brands": [
        "东风"
      ],
      "importance": 42,
      "summary": "东风奕派宣布，奕派M8截至6月28日24时预售订单突破10000台，新车预售价19.98万元起。该车是东风奕派与华为乾崑战略合作升级后的首款落地车型，整合东风汽车、华为乾崑、宁德时代三方技术资源，定位“华派黄金标准大六座”。奕派M8首批搭载华为乾崑智驾ADS 5 Pro，配备27个感知硬件、9个智驾交互信号灯及舱内激光视觉传感器Limera，车长达到5米级别。",
      "takeaway": "华为乾崑方案正成为中大型新能源车快速建立关注度的外部杠杆。",
      "enriched_by": "codex",
      "is_featured": true,
      "has_time": true
    },
    {
      "title": "小鹏MONA L03将于7月2日开启预售 前法拉利设计师操刀 纯电+增程",
      "url": "https://www.autohome.com.cn/news/202606/1315359.html",
      "publish_time": "2026-06-29 11:13",
      "snippet": "",
      "image": "https://www2.autoimg.cn/chejiahaodfs/g34/M09/DE/6F/400x300_0_autohomecar__ChxpWGpB1CmAefW_AAU9Di6OhtE468.png",
      "source": "autohome",
      "source_name": "汽车之家",
      "crawled_at": "2026-06-30T10:31:31.860659+00:00",
      "item_id": "975d978b21b5ab33",
      "publish_ts": 1782702780.0,
      "publish_date": "2026-06-29",
      "image_status": "ok",
      "image_reason": "高置信正文图",
      "category": "技术",
      "brands": [
        "小鹏",
        "法拉利"
      ],
      "importance": 25,
      "summary": "",
      "takeaway": "",
      "enriched_by": "rule",
      "is_featured": false,
      "has_time": true
    },
    {
      "title": "别不信！长城汽车出海，稳赢！",
      "url": "https://www.iautodaily.com/news/brand/biebuxinchangchengqichechuhaiwenying/",
      "publish_time": "2026-06-29 10:57:41",
      "snippet": "当国内汽车市场陷入价格战的时候，一个很容易被忽视的事实正在发生：有人还在靠“降价换销量”，有人已经开始在海外市场“重新打造一整套汽车体系”。 2026年，国内汽车市场的压力肉眼可见。新能源补贴退坡，终端消费需求走弱，行业进入存量竞争的阶段。销量连续下滑，市场焦虑情绪蔓延，为了守住市场份额，一些车企甚至主动加入价格战，靠降价促销、流量噱头争夺市场。 在这样浮躁又承压的行业环境中，长城汽车的发展节奏，却显得格外清醒、稳健。面对市场低迷与外界质疑，长城汽车没有跟风降价内卷，也没有靠营销炒作博取热度。 刚刚召开的长城汽车2025年度股东大会上，总经理穆峰公布的一组核心数据，直观印证了长城汽车的硬核底气，也对外界的诸多质疑进行了强有力的回应： 2025年，长城汽车经营业绩再创新高，全年总营收达到2228.24亿元，同比增长10.2%；整车累计销量132.38万辆，同比增长7.23%。其中，海外市场的表现尤为亮眼，全年出口销量突破50.68万辆，同比增长11.6%，再度刷新品牌出海历史纪录。 实打实的增长数据，说明了长城汽车经营基本面的健康。而不同于部分车企依靠短期降价、政策红利拉动的阶段性增长，长城汽车的业绩增长，具备扎实的内生动力。尤其是在海外市场的持续突破，标志着长城汽车全球化布局，正式迈入高速提质的新阶段。 从巴西到迪拜，从欧洲到南美，长城汽车的出海同样不追求以低价换规模、用性价比换短期销量，而是一步一个脚印，秉持着“在当地，为当地”的核心战略，耐心培育海外市场、打磨海外体系。 魏建军始终把长期主义放在嘴边，长城汽车才能把长期主义植入到企业发展的每一环。不难发现，坚持长期主义的长城汽车，正在依托“生态出海”，走出一条中国汽车品牌高质量全球化的可持续发展之路。 出海没有速胜论，只有长期主义的深耕者，才能赢得全球市场尊重。如果把汽车出海简单理解为“把车卖到国外”，那这件事实在是太简单不过了。但是汽车出海可不仅仅是一种销售行为，而是在海外市场，重建另外一个“自己”。 于是乎，在市场大环境的刺激下，中国汽车出海正在被撕裂成两种不同的模式： 第一种，车企停留在传统出口模式之中，用国内价格战的打法，依靠价格优势，快速进入市场，通过短期销量实现阶段性增长，主打一个快进快出，赚一波钱就走，没有后续服务能力。 这种用低价冲量的出海，才不是什么车企的第二增长曲线，而是提前透支市场。一旦口碑反噬，渠道撤退，利润就只能固化在低端市场，最终被锁死在“靠便宜活着”的陷阱里面。 第二种，则是把自己的整个体系能力带出去，虽然工程量巨大，但车企同步推进本地化研发、本地化制造，以及服务体系建设，才能从“外部供应者”，转变为“本地体系参与者”，进而更长远的布局。 很显然，长城汽车选择的是第二条条路。把工厂建到当地，把研发放到当地，把供应链扎进当地，长城汽车用近30年的海外市场深耕，用真实实践，构建起",
      "image": "https://www.iautodaily.com/wp-content/uploads/2026/06/2026062902570641-480x320.png",
      "source": "iautodaily",
      "source_name": "汽车公社",
      "crawled_at": "2026-06-30T10:30:31.771201+00:00",
      "item_id": "2d46db8d7d3c2c97",
      "publish_ts": 1782701861.0,
      "publish_date": "2026-06-29",
      "image_status": "ok",
      "image_reason": "高置信正文图",
      "category": "市场",
      "brands": [
        "长城"
      ],
      "importance": 45,
      "summary": "长城汽车在2025年度股东大会披露，全年营收2228.24亿元，同比增长10.2%；整车销量132.38万辆，同比增长7.23%；海外出口50.68万辆，同比增长11.6%，刷新出海纪录。文章称，长城没有以国内价格战方式换取短期规模，而是在巴西、迪拜、欧洲、南美等市场推进“在当地，为当地”策略，强调本地研发、制造、供应链和服务体系建设，并把海外视为长期增长曲线。",
      "takeaway": "长城出海的关键不在出口数量，而在能否沉淀本地化体系资产。",
      "enriched_by": "codex",
      "is_featured": true,
      "has_time": true
    },
    {
      "title": "采用新世代外观设计 全新宝马X5外观疑似提前曝光",
      "url": "https://www.autohome.com.cn/news/202606/1315358.html",
      "publish_time": "2026-06-29 10:56",
      "snippet": "",
      "image": "https://img3.autoimg.cn/chejiahaodfs/g34/M0A/DE/7B/400x300_0_autohomecar__ChxpWGpB1LWADs5OAAg6pTK4XVY693.jpg",
      "source": "autohome",
      "source_name": "汽车之家",
      "crawled_at": "2026-06-30T10:31:31.860659+00:00",
      "item_id": "af9f94fefea29d2b",
      "publish_ts": 1782701760.0,
      "publish_date": "2026-06-29",
      "image_status": "ok",
      "image_reason": "高置信正文图",
      "category": "舆情",
      "brands": [
        "宝马"
      ],
      "importance": 14,
      "summary": "",
      "takeaway": "",
      "enriched_by": "rule",
      "is_featured": false,
      "has_time": true
    },
    {
      "title": "估值破200亿，自变量完成多轮重磅融资",
      "url": "https://auto.gasgoo.com/news/202606/29I70463605C601.shtml",
      "publish_time": "2026-06-29 10:18:23",
      "snippet": "获取配套商机，在线申请采购项目 完善公司资料，让采购商深入了解我的生产能力 盖世汽车获悉，自变量机器人已连续完成B+、B++和C轮融资，并已确定性地完成全部交割，投后估值超过200亿元，成为大湾区首个、也是目前唯一估值突破 200 亿元的具身智能企业。 据悉，自变量这几轮融资的投资方阵容也十分豪华，目前已确定的投资方包括中国移动、国家人工智能产业投资基金、红杉中国、IDG 资本、源码资本、达晨财智、中金资本等30多家顶级机构，涵盖互联网巨头资本、产业资本、国家和地方基金。其中小米战投更是已经连续参与三轮融资，用真金白银持续加注。 在此之前，自变量刚刚于4月下旬完成由小米战投与红杉中国联合领投的B轮融资。更早一些时候，自变量还于1月中旬完成了10亿元A++轮融资，并于2月进一步获数亿元新融资，资本热度可见一斑。 作为具身机器人领域的头部玩家，自变量正在积极推进机器人进入家庭场景。此前，自变量已经与58同城合作，将搭载WALL-AS模型的机器人送入真实家庭，与保洁阿姨协同作业，实现全球首次机器人进入家庭，并服务人类复杂的家居生活。据悉，这也是首次机器人在C端复杂环境的大规模落地。 4月21日，自变量进一步推出了搭载其新一代自研具身智能基础模型WALL-B的新一代机器人进家庭计划。WALL-B是基于世界统一模型架构的具身智能基础模型，通过将视觉、语言、动作、物理预测等能力全部放在同一个网络中，从零联合训练，有效消除了模块间的边界和信息损耗。 目前，这批机器人已经开始陆续入驻真实家庭，开启具身智能进入日常生活的“实习期”。 另外，自变量还与好莱客共同出资，成立合资公司：广东智觅量变机器人有限公司。双方将基于好莱客每年近10万家装用户的服务触达和全国渠道网络，以及领先的自研连接技术和全链条生态布局，构建“高端定制+AI智能机器人”的家庭解决方案闭环。 自变量亦自建了数采工厂，并研发了完整的数据管线，能够自动、大规模地执行数据的采集、清洗、标注、质量控制等。其发布的基于自研数采设备XR Zero G0 的数采方案，通过研究将训练模型所需数据成本降低 95%。 这些方案背后，自变量自研了搭载不同模型的量子一号和量子二号，为进入数采工厂和各种落地场景提供坚实支撑。 有意思的是，就在同一天，智平方也对外宣布已于近日完成新系列融资，融资金额近50亿元，投后估值也飙升至200亿元以上，并宣称成为粤港澳大湾区首个估值突破200亿元的具身智能企业。 由此可见，大湾区的具身智能赛道正进入加速发展阶段，资本对该领域头部项目的追捧力度持续升级，区域内的行业竞争也日趋激烈。 据悉，智平方本轮投资方名单实现了“国家队-部委-大湾区-险资-券商-产业方-财投”全链条资本全覆盖。这也是智平方今年完成的第二轮大额融资，在此之前，该公司曾于2月完成B轮融资，规模超10亿元人民币。 智平方成立于2023",
      "image": "https://imagecn.gasgoo.com/moblogo/News/160_110/2026/6/2902170503.jpg",
      "source": "gasgoo",
      "source_name": "盖世汽车",
      "crawled_at": "2026-06-30T10:31:59.098295+00:00",
      "item_id": "0cbcbfad7d55cd64",
      "publish_ts": 1782699503.0,
      "publish_date": "2026-06-29",
      "image_status": "ok",
      "image_reason": "高置信正文图",
      "category": "市场",
      "brands": [
        "小米"
      ],
      "importance": 35,
      "summary": "自变量机器人已连续完成B+、B++和C轮融资并全部交割，投后估值超过200亿元。投资方包括中国移动、国家人工智能产业投资基金、红杉中国、IDG资本、源码资本、达晨财智、中金资本等30多家机构，小米战投已连续参与三轮融资。公司与58同城合作，将搭载WALL-AS模型的机器人送入真实家庭；4月21日又推出搭载WALL-B的新一代机器人进家庭计划，并自建数采工厂。",
      "takeaway": "自变量把家庭场景前置，核心挑战是把演示能力转为可复制服务。",
      "enriched_by": "codex",
      "is_featured": true,
      "has_time": true
    },
    {
      "title": "小鹏MONA L03国内首秀定档7月2日",
      "url": "https://auto.gasgoo.com/news/202606/29I70463600C107.shtml",
      "publish_time": "2026-06-29 10:04:04",
      "snippet": "获取配套商机，在线申请采购项目 完善公司资料，让采购商深入了解我的生产能力 盖世汽车讯 6月29日，小鹏汽车董事长兼CEO何小鹏表示，旗下新车MONA L03将于7月2日迎来中国首场亮相活动，这场发布会在整体安排、产品推广节奏上，和品牌以往新车发布模式存在明显区别。 据官方介绍，本次活动是MONA L03在国内唯一一场发布会，品牌也计划在这场活动中完整、细致地讲解这款车型的产品定位、配置设计以及相关规划安排。 不同于常规先国内全面上市、再择机布局海外的节奏，该车完成国内亮相之后，很快就会奔赴欧洲举办全球发布会并正式上市，海内外两场活动间隔时间很短。紧凑的发布节奏，也意在缩短用户等待周期，更快满足消费者早日订车、提车的需求。 据悉，为方便意向用户近距离实车体验，展车将从7月1日本周三开始陆续运抵小鹏全国各线下门店，感兴趣的消费者可前往门店看车品鉴。产品研发层面，小鹏MONA L03对标30万元级别车型标准打造，采用面向全球市场的一车双能设计思路，依托这样的产品底子，官方认为该车具备突出的性价比表现。 这种先国内首秀预热、紧接着欧洲全球上市的模式，也体现出小鹏加速全球化布局的思路。借助国内单场深度发布会完成产品铺垫，同步衔接欧洲上市节奏，既可以集中做好国内市场前期种草，也能同步推进海外市场投放，统筹海内外推广步调，降低分阶段宣传的冗余周期。 本文地址：http://auto.gasgoo.com/News/2019/05/300656465646I70107904C601.shtml 本文地址：https://auto.gasgoo.com/news/202606/29I70463600C107.shtml 联系邮箱：info@gasgoo.com 求职应聘：021-39197800-8035 简历投递：zhaopin@gasgoo.com 客服微信：gasgoo12 (豆豆) 新闻热线：021-39586122 商务合作：021-39586681 市场合作：021-39197800-8032 研究院项目咨询：021-39197921 盖世汽车社区 盖世大学堂-公开课 英文资讯站 热门内容 数据报告 盖世汽车产业大数据",
      "image": "https://imagecn.gasgoo.com/moblogo/News/160_110/2026/6/2911293119.jpg",
      "source": "gasgoo",
      "source_name": "盖世汽车",
      "crawled_at": "2026-06-30T10:31:59.098295+00:00",
      "item_id": "91d9e77be5be555a",
      "publish_ts": 1782698644.0,
      "publish_date": "2026-06-29",
      "image_status": "ok",
      "image_reason": "高置信正文图",
      "category": "产品",
      "brands": [
        "小鹏"
      ],
      "importance": 35,
      "summary": "6月29日，小鹏汽车董事长兼CEO何小鹏宣布，MONA L03将于7月2日举行中国首场亮相活动。本次活动是该车在国内唯一一场发布会，小鹏计划集中讲解产品定位、配置设计和相关规划。新车国内亮相后将很快赴欧洲举办全球发布会并正式上市，两场活动间隔较短。展车从7月1日起陆续运抵小鹏全国线下门店，供意向用户近距离体验。产品按30万元级车型标准打造，采用面向全球的一车双能设计。",
      "takeaway": "MONA L03同步衔接欧洲上市，显示小鹏正压缩国内外产品投放时差。",
      "enriched_by": "codex",
      "is_featured": true,
      "has_time": true
    },
    {
      "title": "卷轴星空顶+车载吧台 沉浸式体验尊界V800",
      "url": "https://www.autohome.com.cn/drive/202606/1315355.html",
      "publish_time": "2026-06-29 09:00",
      "snippet": "",
      "image": "https://img3.autoimg.cn/chejiahaodfs/g33/M07/D8/E6/Chto52pBKW2AEnXFAA9bJr93WiU265.png",
      "source": "autohome",
      "source_name": "汽车之家",
      "crawled_at": "2026-06-30T10:31:31.860659+00:00",
      "item_id": "e7d3c6125fd4d354",
      "publish_ts": 1782694800.0,
      "publish_date": "2026-06-29",
      "image_status": "ok",
      "image_reason": "高置信正文图",
      "category": "市场",
      "brands": [],
      "importance": 10,
      "summary": "",
      "takeaway": "",
      "enriched_by": "rule",
      "is_featured": false,
      "has_time": true
    },
    {
      "title": "理想汽车正式进入澳门市场",
      "url": "https://auto.gasgoo.com/news/202606/29I70463595C501.shtml",
      "publish_time": "2026-06-29 08:51:27",
      "snippet": "获取配套商机，在线申请采购项目 完善公司资料，让采购商深入了解我的生产能力 盖世汽车获悉，理想汽车已在6月26日宣布正式进入澳门市场，并携手鸿粤集团于澳门金银岛开设澳门首家零售中心。同时，针对当地法规与港澳用户跨境出行需求，理想汽车已完成涵盖车窗玻璃、通信网络及智能座舱等在内的多项产品本地化适配。这是理想汽车持续深耕中国内地市场后，在港澳地区的首次拓展，标志着理想汽车的全球化战略布局迈出重要一步。 此次进入澳门市场，是理想汽车推进全球化战略的重要组成部分，也将进一步提升品牌在港澳地区及亚太市场的影响力。 随着澳门首家零售中心投入运营，当地用户将能够全面体验理想汽车旗下的理想i6及理想i8，享受覆盖购车、交付、售后服务在内的一体化服务体验。面对不同市场的法规和使用场景，理想汽车通过系统性的产品适配，确保澳门用户获得与内地市场同等标准的产品体验。 据悉，针对澳门地区对于车辆玻璃透光率的法规要求，理想汽车联合全球领先汽车玻璃供应商福耀玻璃，专门开发符合当地法规要求的原厂规格双层夹胶非隐私玻璃方案，在满足法规要求的同时，完整保留车辆在静谧性、安全性及隔热性能方面的产品表现。 对于港澳用户频繁往返内地的出行需求，理想汽车同步推进通信网络、智能座舱及导航服务的本地化适配。理想汽车已实现车辆在港澳与内地之间的导航无缝衔接，并针对不同车型提供灵活的通信解决方案。 其中，部分车型支持双卡通信方案，可满足用户跨境使用需求；同时，海外版智能系统已支持包括Apple CarPlay、Spotify等在内的多项本地化应用服务，进一步提升用户日常使用体验。 本文地址：http://auto.gasgoo.com/News/2019/05/300656465646I70107904C601.shtml 本文地址：https://auto.gasgoo.com/news/202606/29I70463595C501.shtml 联系邮箱：info@gasgoo.com 求职应聘：021-39197800-8035 简历投递：zhaopin@gasgoo.com 客服微信：gasgoo12 (豆豆) 新闻热线：021-39586122 商务合作：021-39586681 市场合作：021-39197800-8032 研究院项目咨询：021-39197921 盖世汽车社区 盖世大学堂-公开课 英文资讯站 热门内容 数据报告 盖世汽车产业大数据",
      "image": "",
      "source": "gasgoo",
      "source_name": "盖世汽车",
      "crawled_at": "2026-06-30T10:31:59.098295+00:00",
      "item_id": "19d11cff83d3e3f4",
      "publish_ts": 1782694287.0,
      "publish_date": "2026-06-29",
      "image_status": "rejected",
      "image_reason": "同一图片被超过 3 篇文章复用，按站点装饰图处理",
      "category": "政策",
      "brands": [
        "理想"
      ],
      "importance": 28,
      "summary": "",
      "takeaway": "",
      "enriched_by": "rule",
      "is_featured": false,
      "has_time": true
    },
    {
      "title": "颜值即正义？热度很高，销量却不尽人意 深度试驾尚界Z7T",
      "url": "https://www.autohome.com.cn/drive/202606/1315354.html",
      "publish_time": "2026-06-29 08:00",
      "snippet": "",
      "image": "https://www2.autoimg.cn/chejiahaodfs/g34/M07/D5/F9/400x300_0_autohomecar__ChtpWGpBIniAC-_vABGzOqny5no381.png",
      "source": "autohome",
      "source_name": "汽车之家",
      "crawled_at": "2026-06-30T10:31:31.860659+00:00",
      "item_id": "4dac8674d3215093",
      "publish_ts": 1782691200.0,
      "publish_date": "2026-06-29",
      "image_status": "ok",
      "image_reason": "高置信正文图",
      "category": "市场",
      "brands": [],
      "importance": 17,
      "summary": "",
      "takeaway": "",
      "enriched_by": "rule",
      "is_featured": false,
      "has_time": true
    },
    {
      "title": "丰田Alphard推出日本首款插电混动版",
      "url": "https://auto.gasgoo.com/news/202606/29I70463566C107.shtml",
      "publish_time": "2026-06-29 07:13:00",
      "snippet": "获取配套商机，在线申请采购项目 完善公司资料，让采购商深入了解我的生产能力 盖世汽车讯 丰田汽车近日在日本市场推出Alphard插电式混合动力（PHEV）车型，这是日本首款插电混动版本的迷你厢式车。该车型在延续现款Alphard“舒适移动幸福感”定位的基础上，进一步提升其作为高端商务用车（“ショーファーカー”）的价值。 新款Alphard PHEV搭载18.1千瓦时电池组，纯电续航里程最高可达73公里；在混合动力模式下，综合续航里程超过850公里。当电池电量充足时，车辆可在不启动发动机的情况下以最高约120公里/小时的速度行驶。该PHEV版本仅提供“Executive Lounge”E-Four六座车型，并配备专属19英寸轮毂，以区别于普通混合动力（HEV）版本。尽管新增了驱动电池及相关系统，但车内空间几乎未受影响，仅行李厢地板后端下方的储物盒内部形状有所调整。 与HEV版本相比，PHEV在驾驶性能方面有明显提升。虽然HEV已具备充足的加速能力，但PHEV凭借更高的系统输出功率，在油门响应和加速力度上表现更佳。尽管整车重量有所增加，PHEV的0-100公里/小时加速时间为7.1秒，显著快于HEV的8.8秒。 静谧性方面，PHEV通过多项优化措施，使发动机启停过程几乎无感，营造出极为安静的座舱环境。据描述，其车内对话清晰度在同类车型中较为罕见。推荐使用的“AUTO EV/HV”模式可根据行驶状况自动分配动力输出，在保持高静谧性的同时提升PHEV驾驶体验。 在乘坐舒适性方面，PHEV因电池布局降低了整车重心，提升了行驶稳定性，从而允许减小减震器阻尼力，实现更柔和的滤震效果，且未依赖电子控制悬架系统。此外，新车还新增“Smooth Stop”功能，在制动过程中抑制车身前倾，并在停车瞬间缓释制动力，避免“点头”现象，有助于维持平稳姿态，尤其对驾驶经验较少的用户更为友好。 PHEV版本还拓展了高端商务用车的应用场景，例如可在深夜或清晨安静地穿行住宅区接送乘客、在待机状态下无需启动发动机即可使用空调，以及在外出时通过外放电功能为外部设备供电。尽管售价较HEV版本明显提高，但其在性能、静谧性、舒适性及功能性方面的提升被认为具有较高价值。 该车型信息收录于2026年1月23日发行的《Motor Fan别册 统括系列 Vol.174：2026年国产新型车全览》。 本文地址：http://auto.gasgoo.com/News/2019/05/300656465646I70107904C601.shtml 本文地址：https://auto.gasgoo.com/news/202606/29I70463566C107.shtml 联系邮箱：info@gasgoo.com 求职应聘：021-39197800-8035 简历投递：zhaopin@gasgoo.com 客服微信：g",
      "image": "https://imagecn.gasgoo.com/moblogo/News/160_110/2026/6/2911293119.jpg",
      "source": "gasgoo",
      "source_name": "盖世汽车",
      "crawled_at": "2026-06-30T10:31:59.098295+00:00",
      "item_id": "941fa1a1d5a5f114",
      "publish_ts": 1782688380.0,
      "publish_date": "2026-06-29",
      "image_status": "ok",
      "image_reason": "高置信正文图",
      "category": "技术",
      "brands": [
        "丰田"
      ],
      "importance": 21,
      "summary": "",
      "takeaway": "",
      "enriched_by": "rule",
      "is_featured": false,
      "has_time": true
    },
    {
      "title": "空间配置拉满/反向合资才是版本答案？试驾日产NX8增程版",
      "url": "https://www.autohome.com.cn/drive/202606/1315356.html",
      "publish_time": "2026-06-29 00:10",
      "snippet": "",
      "image": "https://img3.autoimg.cn/chejiahaodfs/g34/M09/D9/11/400x300_0_autohomecar__ChxpV2pBNk6AR-rWAAJYLcsOaNA476.jpg",
      "source": "autohome",
      "source_name": "汽车之家",
      "crawled_at": "2026-06-30T10:31:31.860659+00:00",
      "item_id": "08008af790fe8be7",
      "publish_ts": 1782663000.0,
      "publish_date": "2026-06-29",
      "image_status": "ok",
      "image_reason": "高置信正文图",
      "category": "产品",
      "brands": [
        "日产"
      ],
      "importance": 14,
      "summary": "",
      "takeaway": "",
      "enriched_by": "rule",
      "is_featured": false,
      "has_time": true
    }
  ]
}